Workbook

Sheet Start Here
C2: Sorted. Budget Planner
C3: Ten minutes a week. Every pound, dollar or euro with a job.
C5: How to use it
B6: 1 | C6: Setup tab: Type your budget year, your income sources and what you plan to spend per category each month. Rename or add categories freely (up to 30).
B7: 2 | C7: Transactions tab: Log each payment and paycheck: date, description, pick a category from the dropdown, amount. The example rows are there to show the format: delete them when you start.
B8: 3 | C8: This Month tab: Pick a month from the dropdown. See budget vs actual for every category, what's left, and your Needs / Wants / Savings split against 50/30/20.
B9: 4 | C9: Year Dashboard tab: Twelve months at a glance with charts: income, spending by group, savings rate.
B10: 5 | C10: Debt Payoff tab: List your debts in the order you want to clear them, add any extra monthly payment, and see your debt-free date and total interest.
B11: 6 | C11: Savings Goals tab: Set targets and dates. Sorted tells you how much to put aside each month.
C13: Colour key
C14: Yellow cells are yours to type in. Everything else calculates itself, so you can't break it.
C16: Works in
C17: Microsoft Excel (2010 or newer, Windows and Mac), Google Sheets (File > Import > Upload) and Apple Numbers.
C18: Amounts have no currency symbol, so the planner works in any currency.
C20: Tip: back up a blank copy before you start, so you can reuse it next year.

Sheet Setup
B2: Setup
B3: Set this once. Change it whenever life changes.
B5: Budget year | C5: 2027
B7: Category | C7: Group | D7: Monthly budget | F7: Your plan in one look
B8: Salary | C8: Income | D8: 4200 | F8: Planned income | G8: =SUMIFS($D$8:$D$37,$C$8:$C$37,"Income") -> 4600
B9: Side income | C9: Income | D9: 400 | F9: Planned needs | G9: =SUMIFS($D$8:$D$37,$C$8:$C$37,"Needs") -> 2510
B10: Rent / mortgage | C10: Needs | D10: 1350 | F10: Planned wants | G10: =SUMIFS($D$8:$D$37,$C$8:$C$37,"Wants") -> 645
B11: Utilities | C11: Needs | D11: 180 | F11: Planned savings | G11: =SUMIFS($D$8:$D$37,$C$8:$C$37,"Savings") -> 1045
B12: Groceries | C12: Needs | D12: 450 | F12: Planned debt | G12: =SUMIFS($D$8:$D$37,$C$8:$C$37,"Debt") -> 400
B13: Transport | C13: Needs | D13: 220 | F13: Left to assign | G13: =G8-SUM(G9:G12) -> 0
B14: Insurance | C14: Needs | D14: 160 | F14: Aim for 0: every unit of income gets a job (zero-based budgeting).
B15: Phone & internet | C15: Needs | D15: 90
B16: Health | C16: Needs | D16: 60
B17: Eating out | C17: Wants | D17: 200
B18: Shopping | C18: Wants | D18: 150
B19: Entertainment | C19: Wants | D19: 80
B20: Subscriptions | C20: Wants | D20: 45
B21: Travel | C21: Wants | D21: 120
B22: Gifts | C22: Wants | D22: 50
B23: Emergency fund | C23: Savings | D23: 500
B24: Investing | C24: Savings | D24: 445
B25: Holiday fund | C25: Savings | D25: 100
B26: Credit card | C26: Debt | D26: 250
B27: Student loan | C27: Debt | D27: 150

Sheet Transactions
B2: Transactions
B3: Log money in and money out. Pick categories from the dropdown. The grey columns fill themselves.
B4: Date | C4: Description | D4: Category | E4: Amount | F4: Group | G4: Month | H4: Year
B5: 46388 | C5: Monthly salary | D5: Salary | E5: 4200 | F5: =IF(D5="","",IFERROR(INDEX(Setup!$C$8:$C$37,MATCH(D5,Setup!$B$8:$B$37,0)),"Check category")) -> Income | G5: =IF(B5="","",MONTH(B5)) -> 1 | H5: =IF(B5="","",YEAR(B5)) -> 2027
B6: 46388 | C6: Rent | D6: Rent / mortgage | E6: 1350 | F6: =IF(D6="","",IFERROR(INDEX(Setup!$C$8:$C$37,MATCH(D6,Setup!$B$8:$B$37,0)),"Check category")) -> Needs | G6: =IF(B6="","",MONTH(B6)) -> 1 | H6: =IF(B6="","",YEAR(B6)) -> 2027
B7: 46389 | C7: Emergency fund transfer | D7: Emergency fund | E7: 500 | F7: =IF(D7="","",IFERROR(INDEX(Setup!$C$8:$C$37,MATCH(D7,Setup!$B$8:$B$37,0)),"Check category")) -> Savings | G7: =IF(B7="","",MONTH(B7)) -> 1 | H7: =IF(B7="","",YEAR(B7)) -> 2027
B8: 46389 | C8: Index fund | D8: Investing | E8: 445 | F8: =IF(D8="","",IFERROR(INDEX(Setup!$C$8:$C$37,MATCH(D8,Setup!$B$8:$B$37,0)),"Check category")) -> Savings | G8: =IF(B8="","",MONTH(B8)) -> 1 | H8: =IF(B8="","",YEAR(B8)) -> 2027
B9: 46390 | C9: Electric & water | D9: Utilities | E9: 178.77 | F9: =IF(D9="","",IFERROR(INDEX(Setup!$C$8:$C$37,MATCH(D9,Setup!$B$8:$B$37,0)),"Check category")) -> Needs | G9: =IF(B9="","",MONTH(B9)) -> 1 | H9: =IF(B9="","",YEAR(B9)) -> 2027
B10: 46391 | C10: Weekly shop | D10: Groceries | E10: 95.88 | F10: =IF(D10="","",IFERROR(INDEX(Setup!$C$8:$C$37,MATCH(D10,Setup!$B$8:$B$37,0)),"Check category")) -> Needs | G10: =IF(B10="","",MONTH(B10)) -> 1 | H10: =IF(B10="","",YEAR(B10)) -> 2027
B11: 46392 | C11: Train pass | D11: Transport | E11: 180 | F11: =IF(D11="","",IFERROR(INDEX(Setup!$C$8:$C$37,MATCH(D11,Setup!$B$8:$B$37,0)),"Check category")) -> Needs | G11: =IF(B11="","",MONTH(B11)) -> 1 | H11: =IF(B11="","",YEAR(B11)) -> 2027
B12: 46393 | C12: Streaming + music | D12: Subscriptions | E12: 45 | F12: =IF(D12="","",IFERROR(INDEX(Setup!$C$8:$C$37,MATCH(D12,Setup!$B$8:$B$37,0)),"Check category")) -> Wants | G12: =IF(B12="","",MONTH(B12)) -> 1 | H12: =IF(B12="","",YEAR(B12)) -> 2027
B13: 46395 | C13: Dinner with friends | D13: Eating out | E13: 52.38 | F13: =IF(D13="","",IFERROR(INDEX(Setup!$C$8:$C$37,MATCH(D13,Setup!$B$8:$B$37,0)),"Check category")) -> Wants | G13: =IF(B13="","",MONTH(B13)) -> 1 | H13: =IF(B13="","",YEAR(B13)) -> 2027
B14: 46398 | C14: Weekly shop | D14: Groceries | E14: 102.81 | F14: =IF(D14="","",IFERROR(INDEX(Setup!$C$8:$C$37,MATCH(D14,Setup!$B$8:$B$37,0)),"Check category")) -> Needs | G14: =IF(B14="","",MONTH(B14)) -> 1 | H14: =IF(B14="","",YEAR(B14)) -> 2027
B15: 46399 | C15: Phone + broadband | D15: Phone & internet | E15: 90 | F15: =IF(D15="","",IFERROR(INDEX(Setup!$C$8:$C$37,MATCH(D15,Setup!$B$8:$B$37,0)),"Check category")) -> Needs | G15: =IF(B15="","",MONTH(B15)) -> 1 | H15: =IF(B15="","",YEAR(B15)) -> 2027
B16: 46401 | C16: Freelance logo job | D16: Side income | E16: 350 | F16: =IF(D16="","",IFERROR(INDEX(Setup!$C$8:$C$37,MATCH(D16,Setup!$B$8:$B$37,0)),"Check category")) -> Income | G16: =IF(B16="","",MONTH(B16)) -> 1 | H16: =IF(B16="","",YEAR(B16)) -> 2027
... B70: 46474 | C70: Flights deposit | D70: Travel | E70: 210 | F70: =IF(D70="","",IFERROR(INDEX(Setup!$C$8:$C$37,MATCH(D70,Setup!$B$8:$B$37,0)),"Check category")) -> Wants | G70: =IF(B70="","",MONTH(B70)) -> 3 | H70: =IF(B70="","",YEAR(B70)) -> 2027
F71: =IF(D71="","",IFERROR(INDEX(Setup!$C$8:$C$37,MATCH(D71,Setup!$B$8:$B$37,0)),"Check category")) | G71: =IF(B71="","",MONTH(B71)) | H71: =IF(B71="","",YEAR(B71))
F72: =IF(D72="","",IFERROR(INDEX(Setup!$C$8:$C$37,MATCH(D72,Setup!$B$8:$B$37,0)),"Check category")) | G72: =IF(B72="","",MONTH(B72)) | H72: =IF(B72="","",YEAR(B72))
F73: =IF(D73="","",IFERROR(INDEX(Setup!$C$8:$C$37,MATCH(D73,Setup!$B$8:$B$37,0)),"Check category")) | G73: =IF(B73="","",MONTH(B73)) | H73: =IF(B73="","",YEAR(B73))
F74: =IF(D74="","",IFERROR(INDEX(Setup!$C$8:$C$37,MATCH(D74,Setup!$B$8:$B$37,0)),"Check category")) | G74: =IF(B74="","",MONTH(B74)) | H74: =IF(B74="","",YEAR(B74))
F75: =IF(D75="","",IFERROR(INDEX(Setup!$C$8:$C$37,MATCH(D75,Setup!$B$8:$B$37,0)),"Check category")) | G75: =IF(B75="","",MONTH(B75)) | H75: =IF(B75="","",YEAR(B75))
F76: =IF(D76="","",IFERROR(INDEX(Setup!$C$8:$C$37,MATCH(D76,Setup!$B$8:$B$37,0)),"Check category")) | G76: =IF(B76="","",MONTH(B76)) | H76: =IF(B76="","",YEAR(B76))
F77: =IF(D77="","",IFERROR(INDEX(Setup!$C$8:$C$37,MATCH(D77,Setup!$B$8:$B$37,0)),"Check category")) | G77: =IF(B77="","",MONTH(B77)) | H77: =IF(B77="","",YEAR(B77))
F78: =IF(D78="","",IFERROR(INDEX(Setup!$C$8:$C$37,MATCH(D78,Setup!$B$8:$B$37,0)),"Check category")) | G78: =IF(B78="","",MONTH(B78)) | H78: =IF(B78="","",YEAR(B78))
F79: =IF(D79="","",IFERROR(INDEX(Setup!$C$8:$C$37,MATCH(D79,Setup!$B$8:$B$37,0)),"Check category")) | G79: =IF(B79="","",MONTH(B79)) | H79: =IF(B79="","",YEAR(B79))
F80: =IF(D80="","",IFERROR(INDEX(Setup!$C$8:$C$37,MATCH(D80,Setup!$B$8:$B$37,0)),"Check category")) | G80: =IF(B80="","",MONTH(B80)) | H80: =IF(B80="","",YEAR(B80))
F81: =IF(D81="","",IFERROR(INDEX(Setup!$C$8:$C$37,MATCH(D81,Setup!$B$8:$B$37,0)),"Check category")) | G81: =IF(B81="","",MONTH(B81)) | H81: =IF(B81="","",YEAR(B81))
F82: =IF(D82="","",IFERROR(INDEX(Setup!$C$8:$C$37,MATCH(D82,Setup!$B$8:$B$37,0)),"Check category")) | G82: =IF(B82="","",MONTH(B82)) | H82: =IF(B82="","",YEAR(B82))
... F1504: =IF(D1504="","",IFERROR(INDEX(Setup!$C$8:$C$37,MATCH(D1504,Setup!$B$8:$B$37,0)),"Check category")) | G1504: =IF(B1504="","",MONTH(B1504)) | H1504: =IF(B1504="","",YEAR(B1504))

Sheet This Month
B2: This Month
B3: Pick a month. Everything below updates.
B5: Month | C5: January | E5: =MATCH(C5,{"January","February","March","April","May","June","July","August","September","October","November","December"},0) -> 1 | F5: =Setup!C5 -> 2027
B7: Category | C7: Group | D7: Budget | E7: Actual | F7: Left | G7: Used | I7: Summary
B8: =IF(Setup!B8="","",Setup!B8) -> Salary | C8: =IF(Setup!B8="","",Setup!C8) -> Income | D8: =IF(B8="","",Setup!D8) -> 4200 | E8: =IF(B8="","",SUMIFS(Transactions!$E$5:$E$1504,Transactions!$D$5:$D$1504,B8,Transactions!$G$5:$G$1504,$E$5,Transactions!$H$5:$H$1504,$F$5)) -> 4200 | F8: =IF(B8="","",IF(C8="Income",E8-D8,D8-E8)) -> 0 | G8: =IF(OR(B8="",N(D8)=0),"",E8/D8) -> 1 | I8: Income received | J8: =SUMIFS(Transactions!$E$5:$E$1504,Transactions!$F$5:$F$1504,"Income",Transactions!$G$5:$G$1504,$E$5,Transactions!$H$5:$H$1504,$F$5) -> 4550
B9: =IF(Setup!B9="","",Setup!B9) -> Side income | C9: =IF(Setup!B9="","",Setup!C9) -> Income | D9: =IF(B9="","",Setup!D9) -> 400 | E9: =IF(B9="","",SUMIFS(Transactions!$E$5:$E$1504,Transactions!$D$5:$D$1504,B9,Transactions!$G$5:$G$1504,$E$5,Transactions!$H$5:$H$1504,$F$5)) -> 350 | F9: =IF(B9="","",IF(C9="Income",E9-D9,D9-E9)) -> -50 | G9: =IF(OR(B9="",N(D9)=0),"",E9/D9) -> 0.875 | I9: Spent (needs + wants) | J9: =SUMIFS(Transactions!$E$5:$E$1504,Transactions!$F$5:$F$1504,"Needs",Transactions!$G$5:$G$1504,$E$5,Transactions!$H$5:$H$1504,$F$5)+SUMIFS(Transactions!$E$5:$E$1504,Transactions!$F$5:$F$1504,"Wants",Transactions!$G$5:$G$1504,$E$5,Transactions!$H$5:$H$1504,$F$5) -> 2761.46
B10: =IF(Setup!B10="","",Setup!B10) -> Rent / mortgage | C10: =IF(Setup!B10="","",Setup!C10) -> Needs | D10: =IF(B10="","",Setup!D10) -> 1350 | E10: =IF(B10="","",SUMIFS(Transactions!$E$5:$E$1504,Transactions!$D$5:$D$1504,B10,Transactions!$G$5:$G$1504,$E$5,Transactions!$H$5:$H$1504,$F$5)) -> 1350 | F10: =IF(B10="","",IF(C10="Income",E10-D10,D10-E10)) -> 0 | G10: =IF(OR(B10="",N(D10)=0),"",E10/D10) -> 1 | I10: Saved | J10: =SUMIFS(Transactions!$E$5:$E$1504,Transactions!$F$5:$F$1504,"Savings",Transactions!$G$5:$G$1504,$E$5,Transactions!$H$5:$H$1504,$F$5) -> 945
B11: =IF(Setup!B11="","",Setup!B11) -> Utilities | C11: =IF(Setup!B11="","",Setup!C11) -> Needs | D11: =IF(B11="","",Setup!D11) -> 180 | E11: =IF(B11="","",SUMIFS(Transactions!$E$5:$E$1504,Transactions!$D$5:$D$1504,B11,Transactions!$G$5:$G$1504,$E$5,Transactions!$H$5:$H$1504,$F$5)) -> 178.77 | F11: =IF(B11="","",IF(C11="Income",E11-D11,D11-E11)) -> 1.23 | G11: =IF(OR(B11="",N(D11)=0),"",E11/D11) -> 0.99316667 | I11: Debt paid | J11: =SUMIFS(Transactions!$E$5:$E$1504,Transactions!$F$5:$F$1504,"Debt",Transactions!$G$5:$G$1504,$E$5,Transactions!$H$5:$H$1504,$F$5) -> 400
B12: =IF(Setup!B12="","",Setup!B12) -> Groceries | C12: =IF(Setup!B12="","",Setup!C12) -> Needs | D12: =IF(B12="","",Setup!D12) -> 450 | E12: =IF(B12="","",SUMIFS(Transactions!$E$5:$E$1504,Transactions!$D$5:$D$1504,B12,Transactions!$G$5:$G$1504,$E$5,Transactions!$H$5:$H$1504,$F$5)) -> 427.14 | F12: =IF(B12="","",IF(C12="Income",E12-D12,D12-E12)) -> 22.86 | G12: =IF(OR(B12="",N(D12)=0),"",E12/D12) -> 0.9492 | I12: Left over | J12: =J8-J9-J10-J11 -> 443.54
B13: =IF(Setup!B13="","",Setup!B13) -> Transport | C13: =IF(Setup!B13="","",Setup!C13) -> Needs | D13: =IF(B13="","",Setup!D13) -> 220 | E13: =IF(B13="","",SUMIFS(Transactions!$E$5:$E$1504,Transactions!$D$5:$D$1504,B13,Transactions!$G$5:$G$1504,$E$5,Transactions!$H$5:$H$1504,$F$5)) -> 215.74 | F13: =IF(B13="","",IF(C13="Income",E13-D13,D13-E13)) -> 4.26 | G13: =IF(OR(B13="",N(D13)=0),"",E13/D13) -> 0.98063636
B14: =IF(Setup!B14="","",Setup!B14) -> Insurance | C14: =IF(Setup!B14="","",Setup!C14) -> Needs | D14: =IF(B14="","",Setup!D14) -> 160 | E14: =IF(B14="","",SUMIFS(Transactions!$E$5:$E$1504,Transactions!$D$5:$D$1504,B14,Transactions!$G$5:$G$1504,$E$5,Transactions!$H$5:$H$1504,$F$5)) -> 160 | F14: =IF(B14="","",IF(C14="Income",E14-D14,D14-E14)) -> 0 | G14: =IF(OR(B14="",N(D14)=0),"",E14/D14) -> 1
B15: =IF(Setup!B15="","",Setup!B15) -> Phone & internet | C15: =IF(Setup!B15="","",Setup!C15) -> Needs | D15: =IF(B15="","",Setup!D15) -> 90 | E15: =IF(B15="","",SUMIFS(Transactions!$E$5:$E$1504,Transactions!$D$5:$D$1504,B15,Transactions!$G$5:$G$1504,$E$5,Transactions!$H$5:$H$1504,$F$5)) -> 90 | F15: =IF(B15="","",IF(C15="Income",E15-D15,D15-E15)) -> 0 | G15: =IF(OR(B15="",N(D15)=0),"",E15/D15) -> 1 | I15: 50 / 30 / 20 check
B16: =IF(Setup!B16="","",Setup!B16) -> Health | C16: =IF(Setup!B16="","",Setup!C16) -> Needs | D16: =IF(B16="","",Setup!D16) -> 60 | E16: =IF(B16="","",SUMIFS(Transactions!$E$5:$E$1504,Transactions!$D$5:$D$1504,B16,Transactions!$G$5:$G$1504,$E$5,Transactions!$H$5:$H$1504,$F$5)) -> 0 | F16: =IF(B16="","",IF(C16="Income",E16-D16,D16-E16)) -> 60 | G16: =IF(OR(B16="",N(D16)=0),"",E16/D16) -> 0 | I16: Group | J16: % of income | K16: Target
B17: =IF(Setup!B17="","",Setup!B17) -> Eating out | C17: =IF(Setup!B17="","",Setup!C17) -> Wants | D17: =IF(B17="","",Setup!D17) -> 200 | E17: =IF(B17="","",SUMIFS(Transactions!$E$5:$E$1504,Transactions!$D$5:$D$1504,B17,Transactions!$G$5:$G$1504,$E$5,Transactions!$H$5:$H$1504,$F$5)) -> 80.42 | F17: =IF(B17="","",IF(C17="Income",E17-D17,D17-E17)) -> 119.58 | G17: =IF(OR(B17="",N(D17)=0),"",E17/D17) -> 0.4021 | I17: Needs | J17: =IFERROR((SUMIFS(Transactions!$E$5:$E$1504,Transactions!$F$5:$F$1504,"Needs",Transactions!$G$5:$G$1504,$E$5,Transactions!$H$5:$H$1504,$F$5))/$J$8,0) -> 0.53223077 | K17: 0.5
B18: =IF(Setup!B18="","",Setup!B18) -> Shopping | C18: =IF(Setup!B18="","",Setup!C18) -> Wants | D18: =IF(B18="","",Setup!D18) -> 150 | E18: =IF(B18="","",SUMIFS(Transactions!$E$5:$E$1504,Transactions!$D$5:$D$1504,B18,Transactions!$G$5:$G$1504,$E$5,Transactions!$H$5:$H$1504,$F$5)) -> 175.98 | F18: =IF(B18="","",IF(C18="Income",E18-D18,D18-E18)) -> -25.98 | G18: =IF(OR(B18="",N(D18)=0),"",E18/D18) -> 1.1732 | I18: Wants | J18: =IFERROR((SUMIFS(Transactions!$E$5:$E$1504,Transactions!$F$5:$F$1504,"Wants",Transactions!$G$5:$G$1504,$E$5,Transactions!$H$5:$H$1504,$F$5))/$J$8,0) -> 0.074683516 | K18: 0.3
B19: =IF(Setup!B19="","",Setup!B19) -> Entertainment | C19: =IF(Setup!B19="","",Setup!C19) -> Wants | D19: =IF(B19="","",Setup!D19) -> 80 | E19: =IF(B19="","",SUMIFS(Transactions!$E$5:$E$1504,Transactions!$D$5:$D$1504,B19,Transactions!$G$5:$G$1504,$E$5,Transactions!$H$5:$H$1504,$F$5)) -> 38.41 | F19: =IF(B19="","",IF(C19="Income",E19-D19,D19-E19)) -> 41.59 | G19: =IF(OR(B19="",N(D19)=0),"",E19/D19) -> 0.480125 | I19: Savings | J19: =IFERROR((SUMIFS(Transactions!$E$5:$E$1504,Transactions!$F$5:$F$1504,"Savings",Transactions!$G$5:$G$1504,$E$5,Transactions!$H$5:$H$1504,$F$5)+SUMIFS(Transactions!$E$5:$E$1504,Transactions!$F$5:$F$1504,"Debt",Transactions!$G$5:$G$1504,$E$5,Transactions!$H$5:$H$1504,$F$5))/$J$8,0) -> 0.2956044 | K19: 0.2
B20: =IF(Setup!B20="","",Setup!B20) -> Subscriptions | C20: =IF(Setup!B20="","",Setup!C20) -> Wants | D20: =IF(B20="","",Setup!D20) -> 45 | E20: =IF(B20="","",SUMIFS(Transactions!$E$5:$E$1504,Transactions!$D$5:$D$1504,B20,Transactions!$G$5:$G$1504,$E$5,Transactions!$H$5:$H$1504,$F$5)) -> 45 | F20: =IF(B20="","",IF(C20="Income",E20-D20,D20-E20)) -> 0 | G20: =IF(OR(B20="",N(D20)=0),"",E20/D20) -> 1 | I20: Savings includes debt paid down, as in the classic 50/30/20 rule.
B21: =IF(Setup!B21="","",Setup!B21) -> Travel | C21: =IF(Setup!B21="","",Setup!C21) -> Wants | D21: =IF(B21="","",Setup!D21) -> 120 | E21: =IF(B21="","",SUMIFS(Transactions!$E$5:$E$1504,Transactions!$D$5:$D$1504,B21,Transactions!$G$5:$G$1504,$E$5,Transactions!$H$5:$H$1504,$F$5)) -> 0 | F21: =IF(B21="","",IF(C21="Income",E21-D21,D21-E21)) -> 120 | G21: =IF(OR(B21="",N(D21)=0),"",E21/D21) -> 0
B22: =IF(Setup!B22="","",Setup!B22) -> Gifts | C22: =IF(Setup!B22="","",Setup!C22) -> Wants | D22: =IF(B22="","",Setup!D22) -> 50 | E22: =IF(B22="","",SUMIFS(Transactions!$E$5:$E$1504,Transactions!$D$5:$D$1504,B22,Transactions!$G$5:$G$1504,$E$5,Transactions!$H$5:$H$1504,$F$5)) -> 0 | F22: =IF(B22="","",IF(C22="Income",E22-D22,D22-E22)) -> 50 | G22: =IF(OR(B22="",N(D22)=0),"",E22/D22) -> 0
B23: =IF(Setup!B23="","",Setup!B23) -> Emergency fund | C23: =IF(Setup!B23="","",Setup!C23) -> Savings | D23: =IF(B23="","",Setup!D23) -> 500 | E23: =IF(B23="","",SUMIFS(Transactions!$E$5:$E$1504,Transactions!$D$5:$D$1504,B23,Transactions!$G$5:$G$1504,$E$5,Transactions!$H$5:$H$1504,$F$5)) -> 500 | F23: =IF(B23="","",IF(C23="Income",E23-D23,D23-E23)) -> 0 | G23: =IF(OR(B23="",N(D23)=0),"",E23/D23) -> 1
B24: =IF(Setup!B24="","",Setup!B24) -> Investing | C24: =IF(Setup!B24="","",Setup!C24) -> Savings | D24: =IF(B24="","",Setup!D24) -> 445 | E24: =IF(B24="","",SUMIFS(Transactions!$E$5:$E$1504,Transactions!$D$5:$D$1504,B24,Transactions!$G$5:$G$1504,$E$5,Transactions!$H$5:$H$1504,$F$5)) -> 445 | F24: =IF(B24="","",IF(C24="Income",E24-D24,D24-E24)) -> 0 | G24: =IF(OR(B24="",N(D24)=0),"",E24/D24) -> 1
B25: =IF(Setup!B25="","",Setup!B25) -> Holiday fund | C25: =IF(Setup!B25="","",Setup!C25) -> Savings | D25: =IF(B25="","",Setup!D25) -> 100 | E25: =IF(B25="","",SUMIFS(Transactions!$E$5:$E$1504,Transactions!$D$5:$D$1504,B25,Transactions!$G$5:$G$1504,$E$5,Transactions!$H$5:$H$1504,$F$5)) -> 0 | F25: =IF(B25="","",IF(C25="Income",E25-D25,D25-E25)) -> 100 | G25: =IF(OR(B25="",N(D25)=0),"",E25/D25) -> 0
B26: =IF(Setup!B26="","",Setup!B26) -> Credit card | C26: =IF(Setup!B26="","",Setup!C26) -> Debt | D26: =IF(B26="","",Setup!D26) -> 250 | E26: =IF(B26="","",SUMIFS(Transactions!$E$5:$E$1504,Transactions!$D$5:$D$1504,B26,Transactions!$G$5:$G$1504,$E$5,Transactions!$H$5:$H$1504,$F$5)) -> 250 | F26: =IF(B26="","",IF(C26="Income",E26-D26,D26-E26)) -> 0 | G26: =IF(OR(B26="",N(D26)=0),"",E26/D26) -> 1
B27: =IF(Setup!B27="","",Setup!B27) -> Student loan | C27: =IF(Setup!B27="","",Setup!C27) -> Debt | D27: =IF(B27="","",Setup!D27) -> 150 | E27: =IF(B27="","",SUMIFS(Transactions!$E$5:$E$1504,Transactions!$D$5:$D$1504,B27,Transactions!$G$5:$G$1504,$E$5,Transactions!$H$5:$H$1504,$F$5)) -> 150 | F27: =IF(B27="","",IF(C27="Income",E27-D27,D27-E27)) -> 0 | G27: =IF(OR(B27="",N(D27)=0),"",E27/D27) -> 1
B28: =IF(Setup!B28="","",Setup!B28) | C28: =IF(Setup!B28="","",Setup!C28) | D28: =IF(B28="","",Setup!D28) | E28: =IF(B28="","",SUMIFS(Transactions!$E$5:$E$1504,Transactions!$D$5:$D$1504,B28,Transactions!$G$5:$G$1504,$E$5,Transactions!$H$5:$H$1504,$F$5)) | F28: =IF(B28="","",IF(C28="Income",E28-D28,D28-E28)) | G28: =IF(OR(B28="",N(D28)=0),"",E28/D28)
B29: =IF(Setup!B29="","",Setup!B29) | C29: =IF(Setup!B29="","",Setup!C29) | D29: =IF(B29="","",Setup!D29) | E29: =IF(B29="","",SUMIFS(Transactions!$E$5:$E$1504,Transactions!$D$5:$D$1504,B29,Transactions!$G$5:$G$1504,$E$5,Transactions!$H$5:$H$1504,$F$5)) | F29: =IF(B29="","",IF(C29="Income",E29-D29,D29-E29)) | G29: =IF(OR(B29="",N(D29)=0),"",E29/D29)
B30: =IF(Setup!B30="","",Setup!B30) | C30: =IF(Setup!B30="","",Setup!C30) | D30: =IF(B30="","",Setup!D30) | E30: =IF(B30="","",SUMIFS(Transactions!$E$5:$E$1504,Transactions!$D$5:$D$1504,B30,Transactions!$G$5:$G$1504,$E$5,Transactions!$H$5:$H$1504,$F$5)) | F30: =IF(B30="","",IF(C30="Income",E30-D30,D30-E30)) | G30: =IF(OR(B30="",N(D30)=0),"",E30/D30)
B31: =IF(Setup!B31="","",Setup!B31) | C31: =IF(Setup!B31="","",Setup!C31) | D31: =IF(B31="","",Setup!D31) | E31: =IF(B31="","",SUMIFS(Transactions!$E$5:$E$1504,Transactions!$D$5:$D$1504,B31,Transactions!$G$5:$G$1504,$E$5,Transactions!$H$5:$H$1504,$F$5)) | F31: =IF(B31="","",IF(C31="Income",E31-D31,D31-E31)) | G31: =IF(OR(B31="",N(D31)=0),"",E31/D31)
B32: =IF(Setup!B32="","",Setup!B32) | C32: =IF(Setup!B32="","",Setup!C32) | D32: =IF(B32="","",Setup!D32) | E32: =IF(B32="","",SUMIFS(Transactions!$E$5:$E$1504,Transactions!$D$5:$D$1504,B32,Transactions!$G$5:$G$1504,$E$5,Transactions!$H$5:$H$1504,$F$5)) | F32: =IF(B32="","",IF(C32="Income",E32-D32,D32-E32)) | G32: =IF(OR(B32="",N(D32)=0),"",E32/D32)
... B37: =IF(Setup!B37="","",Setup!B37) | C37: =IF(Setup!B37="","",Setup!C37) | D37: =IF(B37="","",Setup!D37) | E37: =IF(B37="","",SUMIFS(Transactions!$E$5:$E$1504,Transactions!$D$5:$D$1504,B37,Transactions!$G$5:$G$1504,$E$5,Transactions!$H$5:$H$1504,$F$5)) | F37: =IF(B37="","",IF(C37="Income",E37-D37,D37-E37)) | G37: =IF(OR(B37="",N(D37)=0),"",E37/D37)

Sheet Year Dashboard
B2: Year Dashboard
B3: Your year in one screen.
B4: ="Year "&Setup!C5 -> Year 2027
B6: Month | C6: Income | D6: Needs | E6: Wants | F6: Savings | G6: Debt | H6: Left over | I6: Saving rate
B7: Jan | C7: =SUMIFS(Transactions!$E$5:$E$1504,Transactions!$F$5:$F$1504,"Income",Transactions!$G$5:$G$1504,1,Transactions!$H$5:$H$1504,Setup!$C$5) -> 4550 | D7: =SUMIFS(Transactions!$E$5:$E$1504,Transactions!$F$5:$F$1504,"Needs",Transactions!$G$5:$G$1504,1,Transactions!$H$5:$H$1504,Setup!$C$5) -> 2421.65 | E7: =SUMIFS(Transactions!$E$5:$E$1504,Transactions!$F$5:$F$1504,"Wants",Transactions!$G$5:$G$1504,1,Transactions!$H$5:$H$1504,Setup!$C$5) -> 339.81 | F7: =SUMIFS(Transactions!$E$5:$E$1504,Transactions!$F$5:$F$1504,"Savings",Transactions!$G$5:$G$1504,1,Transactions!$H$5:$H$1504,Setup!$C$5) -> 945 | G7: =SUMIFS(Transactions!$E$5:$E$1504,Transactions!$F$5:$F$1504,"Debt",Transactions!$G$5:$G$1504,1,Transactions!$H$5:$H$1504,Setup!$C$5) -> 400 | H7: =C7-SUM(D7:G7) -> 443.54 | I7: =IF(C7=0,"",(F7+G7)/C7) -> 0.2956044
B8: Feb | C8: =SUMIFS(Transactions!$E$5:$E$1504,Transactions!$F$5:$F$1504,"Income",Transactions!$G$5:$G$1504,2,Transactions!$H$5:$H$1504,Setup!$C$5) -> 4720 | D8: =SUMIFS(Transactions!$E$5:$E$1504,Transactions!$F$5:$F$1504,"Needs",Transactions!$G$5:$G$1504,2,Transactions!$H$5:$H$1504,Setup!$C$5) -> 2427.05 | E8: =SUMIFS(Transactions!$E$5:$E$1504,Transactions!$F$5:$F$1504,"Wants",Transactions!$G$5:$G$1504,2,Transactions!$H$5:$H$1504,Setup!$C$5) -> 321.72 | F8: =SUMIFS(Transactions!$E$5:$E$1504,Transactions!$F$5:$F$1504,"Savings",Transactions!$G$5:$G$1504,2,Transactions!$H$5:$H$1504,Setup!$C$5) -> 945 | G8: =SUMIFS(Transactions!$E$5:$E$1504,Transactions!$F$5:$F$1504,"Debt",Transactions!$G$5:$G$1504,2,Transactions!$H$5:$H$1504,Setup!$C$5) -> 400 | H8: =C8-SUM(D8:G8) -> 626.23 | I8: =IF(C8=0,"",(F8+G8)/C8) -> 0.28495763
B9: Mar | C9: =SUMIFS(Transactions!$E$5:$E$1504,Transactions!$F$5:$F$1504,"Income",Transactions!$G$5:$G$1504,3,Transactions!$H$5:$H$1504,Setup!$C$5) -> 4600 | D9: =SUMIFS(Transactions!$E$5:$E$1504,Transactions!$F$5:$F$1504,"Needs",Transactions!$G$5:$G$1504,3,Transactions!$H$5:$H$1504,Setup!$C$5) -> 2496.16 | E9: =SUMIFS(Transactions!$E$5:$E$1504,Transactions!$F$5:$F$1504,"Wants",Transactions!$G$5:$G$1504,3,Transactions!$H$5:$H$1504,Setup!$C$5) -> 454.69 | F9: =SUMIFS(Transactions!$E$5:$E$1504,Transactions!$F$5:$F$1504,"Savings",Transactions!$G$5:$G$1504,3,Transactions!$H$5:$H$1504,Setup!$C$5) -> 945 | G9: =SUMIFS(Transactions!$E$5:$E$1504,Transactions!$F$5:$F$1504,"Debt",Transactions!$G$5:$G$1504,3,Transactions!$H$5:$H$1504,Setup!$C$5) -> 400 | H9: =C9-SUM(D9:G9) -> 304.15 | I9: =IF(C9=0,"",(F9+G9)/C9) -> 0.2923913
B10: Apr | C10: =SUMIFS(Transactions!$E$5:$E$1504,Transactions!$F$5:$F$1504,"Income",Transactions!$G$5:$G$1504,4,Transactions!$H$5:$H$1504,Setup!$C$5) -> 0 | D10: =SUMIFS(Transactions!$E$5:$E$1504,Transactions!$F$5:$F$1504,"Needs",Transactions!$G$5:$G$1504,4,Transactions!$H$5:$H$1504,Setup!$C$5) -> 0 | E10: =SUMIFS(Transactions!$E$5:$E$1504,Transactions!$F$5:$F$1504,"Wants",Transactions!$G$5:$G$1504,4,Transactions!$H$5:$H$1504,Setup!$C$5) -> 0 | F10: =SUMIFS(Transactions!$E$5:$E$1504,Transactions!$F$5:$F$1504,"Savings",Transactions!$G$5:$G$1504,4,Transactions!$H$5:$H$1504,Setup!$C$5) -> 0 | G10: =SUMIFS(Transactions!$E$5:$E$1504,Transactions!$F$5:$F$1504,"Debt",Transactions!$G$5:$G$1504,4,Transactions!$H$5:$H$1504,Setup!$C$5) -> 0 | H10: =C10-SUM(D10:G10) -> 0 | I10: =IF(C10=0,"",(F10+G10)/C10)
B11: May | C11: =SUMIFS(Transactions!$E$5:$E$1504,Transactions!$F$5:$F$1504,"Income",Transactions!$G$5:$G$1504,5,Transactions!$H$5:$H$1504,Setup!$C$5) -> 0 | D11: =SUMIFS(Transactions!$E$5:$E$1504,Transactions!$F$5:$F$1504,"Needs",Transactions!$G$5:$G$1504,5,Transactions!$H$5:$H$1504,Setup!$C$5) -> 0 | E11: =SUMIFS(Transactions!$E$5:$E$1504,Transactions!$F$5:$F$1504,"Wants",Transactions!$G$5:$G$1504,5,Transactions!$H$5:$H$1504,Setup!$C$5) -> 0 | F11: =SUMIFS(Transactions!$E$5:$E$1504,Transactions!$F$5:$F$1504,"Savings",Transactions!$G$5:$G$1504,5,Transactions!$H$5:$H$1504,Setup!$C$5) -> 0 | G11: =SUMIFS(Transactions!$E$5:$E$1504,Transactions!$F$5:$F$1504,"Debt",Transactions!$G$5:$G$1504,5,Transactions!$H$5:$H$1504,Setup!$C$5) -> 0 | H11: =C11-SUM(D11:G11) -> 0 | I11: =IF(C11=0,"",(F11+G11)/C11)
B12: Jun | C12: =SUMIFS(Transactions!$E$5:$E$1504,Transactions!$F$5:$F$1504,"Income",Transactions!$G$5:$G$1504,6,Transactions!$H$5:$H$1504,Setup!$C$5) -> 0 | D12: =SUMIFS(Transactions!$E$5:$E$1504,Transactions!$F$5:$F$1504,"Needs",Transactions!$G$5:$G$1504,6,Transactions!$H$5:$H$1504,Setup!$C$5) -> 0 | E12: =SUMIFS(Transactions!$E$5:$E$1504,Transactions!$F$5:$F$1504,"Wants",Transactions!$G$5:$G$1504,6,Transactions!$H$5:$H$1504,Setup!$C$5) -> 0 | F12: =SUMIFS(Transactions!$E$5:$E$1504,Transactions!$F$5:$F$1504,"Savings",Transactions!$G$5:$G$1504,6,Transactions!$H$5:$H$1504,Setup!$C$5) -> 0 | G12: =SUMIFS(Transactions!$E$5:$E$1504,Transactions!$F$5:$F$1504,"Debt",Transactions!$G$5:$G$1504,6,Transactions!$H$5:$H$1504,Setup!$C$5) -> 0 | H12: =C12-SUM(D12:G12) -> 0 | I12: =IF(C12=0,"",(F12+G12)/C12)
B13: Jul | C13: =SUMIFS(Transactions!$E$5:$E$1504,Transactions!$F$5:$F$1504,"Income",Transactions!$G$5:$G$1504,7,Transactions!$H$5:$H$1504,Setup!$C$5) -> 0 | D13: =SUMIFS(Transactions!$E$5:$E$1504,Transactions!$F$5:$F$1504,"Needs",Transactions!$G$5:$G$1504,7,Transactions!$H$5:$H$1504,Setup!$C$5) -> 0 | E13: =SUMIFS(Transactions!$E$5:$E$1504,Transactions!$F$5:$F$1504,"Wants",Transactions!$G$5:$G$1504,7,Transactions!$H$5:$H$1504,Setup!$C$5) -> 0 | F13: =SUMIFS(Transactions!$E$5:$E$1504,Transactions!$F$5:$F$1504,"Savings",Transactions!$G$5:$G$1504,7,Transactions!$H$5:$H$1504,Setup!$C$5) -> 0 | G13: =SUMIFS(Transactions!$E$5:$E$1504,Transactions!$F$5:$F$1504,"Debt",Transactions!$G$5:$G$1504,7,Transactions!$H$5:$H$1504,Setup!$C$5) -> 0 | H13: =C13-SUM(D13:G13) -> 0 | I13: =IF(C13=0,"",(F13+G13)/C13)
B14: Aug | C14: =SUMIFS(Transactions!$E$5:$E$1504,Transactions!$F$5:$F$1504,"Income",Transactions!$G$5:$G$1504,8,Transactions!$H$5:$H$1504,Setup!$C$5) -> 0 | D14: =SUMIFS(Transactions!$E$5:$E$1504,Transactions!$F$5:$F$1504,"Needs",Transactions!$G$5:$G$1504,8,Transactions!$H$5:$H$1504,Setup!$C$5) -> 0 | E14: =SUMIFS(Transactions!$E$5:$E$1504,Transactions!$F$5:$F$1504,"Wants",Transactions!$G$5:$G$1504,8,Transactions!$H$5:$H$1504,Setup!$C$5) -> 0 | F14: =SUMIFS(Transactions!$E$5:$E$1504,Transactions!$F$5:$F$1504,"Savings",Transactions!$G$5:$G$1504,8,Transactions!$H$5:$H$1504,Setup!$C$5) -> 0 | G14: =SUMIFS(Transactions!$E$5:$E$1504,Transactions!$F$5:$F$1504,"Debt",Transactions!$G$5:$G$1504,8,Transactions!$H$5:$H$1504,Setup!$C$5) -> 0 | H14: =C14-SUM(D14:G14) -> 0 | I14: =IF(C14=0,"",(F14+G14)/C14)
B15: Sep | C15: =SUMIFS(Transactions!$E$5:$E$1504,Transactions!$F$5:$F$1504,"Income",Transactions!$G$5:$G$1504,9,Transactions!$H$5:$H$1504,Setup!$C$5) -> 0 | D15: =SUMIFS(Transactions!$E$5:$E$1504,Transactions!$F$5:$F$1504,"Needs",Transactions!$G$5:$G$1504,9,Transactions!$H$5:$H$1504,Setup!$C$5) -> 0 | E15: =SUMIFS(Transactions!$E$5:$E$1504,Transactions!$F$5:$F$1504,"Wants",Transactions!$G$5:$G$1504,9,Transactions!$H$5:$H$1504,Setup!$C$5) -> 0 | F15: =SUMIFS(Transactions!$E$5:$E$1504,Transactions!$F$5:$F$1504,"Savings",Transactions!$G$5:$G$1504,9,Transactions!$H$5:$H$1504,Setup!$C$5) -> 0 | G15: =SUMIFS(Transactions!$E$5:$E$1504,Transactions!$F$5:$F$1504,"Debt",Transactions!$G$5:$G$1504,9,Transactions!$H$5:$H$1504,Setup!$C$5) -> 0 | H15: =C15-SUM(D15:G15) -> 0 | I15: =IF(C15=0,"",(F15+G15)/C15)
B16: Oct | C16: =SUMIFS(Transactions!$E$5:$E$1504,Transactions!$F$5:$F$1504,"Income",Transactions!$G$5:$G$1504,10,Transactions!$H$5:$H$1504,Setup!$C$5) -> 0 | D16: =SUMIFS(Transactions!$E$5:$E$1504,Transactions!$F$5:$F$1504,"Needs",Transactions!$G$5:$G$1504,10,Transactions!$H$5:$H$1504,Setup!$C$5) -> 0 | E16: =SUMIFS(Transactions!$E$5:$E$1504,Transactions!$F$5:$F$1504,"Wants",Transactions!$G$5:$G$1504,10,Transactions!$H$5:$H$1504,Setup!$C$5) -> 0 | F16: =SUMIFS(Transactions!$E$5:$E$1504,Transactions!$F$5:$F$1504,"Savings",Transactions!$G$5:$G$1504,10,Transactions!$H$5:$H$1504,Setup!$C$5) -> 0 | G16: =SUMIFS(Transactions!$E$5:$E$1504,Transactions!$F$5:$F$1504,"Debt",Transactions!$G$5:$G$1504,10,Transactions!$H$5:$H$1504,Setup!$C$5) -> 0 | H16: =C16-SUM(D16:G16) -> 0 | I16: =IF(C16=0,"",(F16+G16)/C16)
B17: Nov | C17: =SUMIFS(Transactions!$E$5:$E$1504,Transactions!$F$5:$F$1504,"Income",Transactions!$G$5:$G$1504,11,Transactions!$H$5:$H$1504,Setup!$C$5) -> 0 | D17: =SUMIFS(Transactions!$E$5:$E$1504,Transactions!$F$5:$F$1504,"Needs",Transactions!$G$5:$G$1504,11,Transactions!$H$5:$H$1504,Setup!$C$5) -> 0 | E17: =SUMIFS(Transactions!$E$5:$E$1504,Transactions!$F$5:$F$1504,"Wants",Transactions!$G$5:$G$1504,11,Transactions!$H$5:$H$1504,Setup!$C$5) -> 0 | F17: =SUMIFS(Transactions!$E$5:$E$1504,Transactions!$F$5:$F$1504,"Savings",Transactions!$G$5:$G$1504,11,Transactions!$H$5:$H$1504,Setup!$C$5) -> 0 | G17: =SUMIFS(Transactions!$E$5:$E$1504,Transactions!$F$5:$F$1504,"Debt",Transactions!$G$5:$G$1504,11,Transactions!$H$5:$H$1504,Setup!$C$5) -> 0 | H17: =C17-SUM(D17:G17) -> 0 | I17: =IF(C17=0,"",(F17+G17)/C17)
B18: Dec | C18: =SUMIFS(Transactions!$E$5:$E$1504,Transactions!$F$5:$F$1504,"Income",Transactions!$G$5:$G$1504,12,Transactions!$H$5:$H$1504,Setup!$C$5) -> 0 | D18: =SUMIFS(Transactions!$E$5:$E$1504,Transactions!$F$5:$F$1504,"Needs",Transactions!$G$5:$G$1504,12,Transactions!$H$5:$H$1504,Setup!$C$5) -> 0 | E18: =SUMIFS(Transactions!$E$5:$E$1504,Transactions!$F$5:$F$1504,"Wants",Transactions!$G$5:$G$1504,12,Transactions!$H$5:$H$1504,Setup!$C$5) -> 0 | F18: =SUMIFS(Transactions!$E$5:$E$1504,Transactions!$F$5:$F$1504,"Savings",Transactions!$G$5:$G$1504,12,Transactions!$H$5:$H$1504,Setup!$C$5) -> 0 | G18: =SUMIFS(Transactions!$E$5:$E$1504,Transactions!$F$5:$F$1504,"Debt",Transactions!$G$5:$G$1504,12,Transactions!$H$5:$H$1504,Setup!$C$5) -> 0 | H18: =C18-SUM(D18:G18) -> 0 | I18: =IF(C18=0,"",(F18+G18)/C18)
B19: Total | C19: =SUM(C7:C18) -> 13870 | D19: =SUM(D7:D18) -> 7344.86 | E19: =SUM(E7:E18) -> 1116.22 | F19: =SUM(F7:F18) -> 2835 | G19: =SUM(G7:G18) -> 1200 | H19: =SUM(H7:H18) -> 1373.92 | I19: =IF(C19=0,"",(F19+G19)/C19) -> 0.29091565

Sheet Debt Payoff
B2: Debt Payoff
B3: List debts in the order you want to clear them. Snowball: smallest balance first. Avalanche: highest interest first.
B5: Debt | C5: Balance | D5: APR | E5: Min payment | F5: Paid off in | H5: Your plan
B6: Credit card | C6: 3200 | D6: 0.229 | E6: 95 | F6: =IF(N(C6)=0,"",IF(COUNTIF(U41:U160,">0.005")>=120,"10+ years",TEXT(EDATE($C$13,COUNTIF(U41:U160,">0.005")),"mmm yyyy"))) -> Apr 2028 | H6: Debt-free in | I6: =IF(COUNTIF(Z41:Z160,">0.005")>=120,"10+ years",COUNTIF(Z41:Z160,">0.005")+1&" months") -> 46 months
B7: Car loan | C7: 8400 | D7: 0.065 | E7: 240 | F7: =IF(N(C7)=0,"",IF(COUNTIF(V41:V160,">0.005")>=120,"10+ years",TEXT(EDATE($C$13,COUNTIF(V41:V160,">0.005")),"mmm yyyy"))) -> Mar 2029 | H7: Debt-free by | I7: =IF(COUNTIF(Z41:Z160,">0.005")>=120,"Pay more each month",TEXT(EDATE($C$13,COUNTIF(Z41:Z160,">0.005")),"mmmm yyyy")) -> October 2030
B8: Student loan | C8: 14500 | D8: 0.05 | E8: 160 | F8: =IF(N(C8)=0,"",IF(COUNTIF(W41:W160,">0.005")>=120,"10+ years",TEXT(EDATE($C$13,COUNTIF(W41:W160,">0.005")),"mmm yyyy"))) -> Oct 2030 | H8: Starting debt | I8: =SUM(C6:C10) -> 26100
F9: =IF(N(C9)=0,"",IF(COUNTIF(X41:X160,">0.005")>=120,"10+ years",TEXT(EDATE($C$13,COUNTIF(X41:X160,">0.005")),"mmm yyyy"))) | H9: Total interest you'll pay | I9: =SUM(P41:T160)-I8 -> 3220.6467
F10: =IF(N(C10)=0,"",IF(COUNTIF(Y41:Y160,">0.005")>=120,"10+ years",TEXT(EDATE($C$13,COUNTIF(Y41:Y160,">0.005")),"mmm yyyy")))
H11: =IF(C14<SUM(E6:E10),"Total paid is below your minimum payments. Raise the extra amount.","")
B12: Extra paid each month | C12: 150
B13: First payment month | C13: 46388
B14: Total paid each month | C14: =SUM(E6:E10)+C12 -> 645
B39: Month-by-month schedule (calculated)
J40: Month | K40: Owed 1 | L40: Owed 2 | M40: Owed 3 | N40: Owed 4 | O40: Owed 5 | P40: Pay 1 | Q40: Pay 2 | R40: Pay 3 | S40: Pay 4 | T40: Pay 5 | U40: Balance 1 | V40: Balance 2 | W40: Balance 3 | X40: Balance 4 | Y40: Balance 5 | Z40: Total balance
J41: =EDATE($C$13,0) -> 46388 | K41: =N($C$6)*(1+N($D$6)/12) -> 3261.0667 | L41: =N($C$7)*(1+N($D$7)/12) -> 8445.5 | M41: =N($C$8)*(1+N($D$8)/12) -> 14560.417 | N41: =N($C$9)*(1+N($D$9)/12) -> 0 | O41: =N($C$10)*(1+N($D$10)/12) -> 0 | P41: =MAX(0,MIN(K41,$C$14-(0)-(MIN(L41,N($E$7))+MIN(M41,N($E$8))+MIN(N41,N($E$9))+MIN(O41,N($E$10))))) -> 245 | Q41: =MAX(0,MIN(L41,$C$14-(P41)-(MIN(M41,N($E$8))+MIN(N41,N($E$9))+MIN(O41,N($E$10))))) -> 240 | R41: =MAX(0,MIN(M41,$C$14-(P41+Q41)-(MIN(N41,N($E$9))+MIN(O41,N($E$10))))) -> 160 | S41: =MAX(0,MIN(N41,$C$14-(P41+Q41+R41)-(MIN(O41,N($E$10))))) -> 0 | T41: =MAX(0,MIN(O41,$C$14-(P41+Q41+R41+S41)-(0))) -> 0 | U41: =ROUND(K41-P41,2) -> 3016.07 | V41: =ROUND(L41-Q41,2) -> 8205.5 | W41: =ROUND(M41-R41,2) -> 14400.42 | X41: =ROUND(N41-S41,2) -> 0 | Y41: =ROUND(O41-T41,2) -> 0 | Z41: =SUM(U41:Y41) -> 25621.99
J42: =EDATE($C$13,1) -> 46419 | K42: =U41*(1+N($D$6)/12) -> 3073.6267 | L42: =V41*(1+N($D$7)/12) -> 8249.9465 | M42: =W41*(1+N($D$8)/12) -> 14460.422 | N42: =X41*(1+N($D$9)/12) -> 0 | O42: =Y41*(1+N($D$10)/12) -> 0 | P42: =MAX(0,MIN(K42,$C$14-(0)-(MIN(L42,N($E$7))+MIN(M42,N($E$8))+MIN(N42,N($E$9))+MIN(O42,N($E$10))))) -> 245 | Q42: =MAX(0,MIN(L42,$C$14-(P42)-(MIN(M42,N($E$8))+MIN(N42,N($E$9))+MIN(O42,N($E$10))))) -> 240 | R42: =MAX(0,MIN(M42,$C$14-(P42+Q42)-(MIN(N42,N($E$9))+MIN(O42,N($E$10))))) -> 160 | S42: =MAX(0,MIN(N42,$C$14-(P42+Q42+R42)-(MIN(O42,N($E$10))))) -> 0 | T42: =MAX(0,MIN(O42,$C$14-(P42+Q42+R42+S42)-(0))) -> 0 | U42: =ROUND(K42-P42,2) -> 2828.63 | V42: =ROUND(L42-Q42,2) -> 8009.95 | W42: =ROUND(M42-R42,2) -> 14300.42 | X42: =ROUND(N42-S42,2) -> 0 | Y42: =ROUND(O42-T42,2) -> 0 | Z42: =SUM(U42:Y42) -> 25139
J43: =EDATE($C$13,2) -> 46447 | K43: =U42*(1+N($D$6)/12) -> 2882.6097 | L43: =V42*(1+N($D$7)/12) -> 8053.3372 | M43: =W42*(1+N($D$8)/12) -> 14360.005 | N43: =X42*(1+N($D$9)/12) -> 0 | O43: =Y42*(1+N($D$10)/12) -> 0 | P43: =MAX(0,MIN(K43,$C$14-(0)-(MIN(L43,N($E$7))+MIN(M43,N($E$8))+MIN(N43,N($E$9))+MIN(O43,N($E$10))))) -> 245 | Q43: =MAX(0,MIN(L43,$C$14-(P43)-(MIN(M43,N($E$8))+MIN(N43,N($E$9))+MIN(O43,N($E$10))))) -> 240 | R43: =MAX(0,MIN(M43,$C$14-(P43+Q43)-(MIN(N43,N($E$9))+MIN(O43,N($E$10))))) -> 160 | S43: =MAX(0,MIN(N43,$C$14-(P43+Q43+R43)-(MIN(O43,N($E$10))))) -> 0 | T43: =MAX(0,MIN(O43,$C$14-(P43+Q43+R43+S43)-(0))) -> 0 | U43: =ROUND(K43-P43,2) -> 2637.61 | V43: =ROUND(L43-Q43,2) -> 7813.34 | W43: =ROUND(M43-R43,2) -> 14200.01 | X43: =ROUND(N43-S43,2) -> 0 | Y43: =ROUND(O43-T43,2) -> 0 | Z43: =SUM(U43:Y43) -> 24650.96
J44: =EDATE($C$13,3) -> 46478 | K44: =U43*(1+N($D$6)/12) -> 2687.9444 | L44: =V43*(1+N($D$7)/12) -> 7855.6623 | M44: =W43*(1+N($D$8)/12) -> 14259.177 | N44: =X43*(1+N($D$9)/12) -> 0 | O44: =Y43*(1+N($D$10)/12) -> 0 | P44: =MAX(0,MIN(K44,$C$14-(0)-(MIN(L44,N($E$7))+MIN(M44,N($E$8))+MIN(N44,N($E$9))+MIN(O44,N($E$10))))) -> 245 | Q44: =MAX(0,MIN(L44,$C$14-(P44)-(MIN(M44,N($E$8))+MIN(N44,N($E$9))+MIN(O44,N($E$10))))) -> 240 | R44: =MAX(0,MIN(M44,$C$14-(P44+Q44)-(MIN(N44,N($E$9))+MIN(O44,N($E$10))))) -> 160 | S44: =MAX(0,MIN(N44,$C$14-(P44+Q44+R44)-(MIN(O44,N($E$10))))) -> 0 | T44: =MAX(0,MIN(O44,$C$14-(P44+Q44+R44+S44)-(0))) -> 0 | U44: =ROUND(K44-P44,2) -> 2442.94 | V44: =ROUND(L44-Q44,2) -> 7615.66 | W44: =ROUND(M44-R44,2) -> 14099.18 | X44: =ROUND(N44-S44,2) -> 0 | Y44: =ROUND(O44-T44,2) -> 0 | Z44: =SUM(U44:Y44) -> 24157.78
J45: =EDATE($C$13,4) -> 46508 | K45: =U44*(1+N($D$6)/12) -> 2489.5594 | L45: =V44*(1+N($D$7)/12) -> 7656.9115 | M45: =W44*(1+N($D$8)/12) -> 14157.927 | N45: =X44*(1+N($D$9)/12) -> 0 | O45: =Y44*(1+N($D$10)/12) -> 0 | P45: =MAX(0,MIN(K45,$C$14-(0)-(MIN(L45,N($E$7))+MIN(M45,N($E$8))+MIN(N45,N($E$9))+MIN(O45,N($E$10))))) -> 245 | Q45: =MAX(0,MIN(L45,$C$14-(P45)-(MIN(M45,N($E$8))+MIN(N45,N($E$9))+MIN(O45,N($E$10))))) -> 240 | R45: =MAX(0,MIN(M45,$C$14-(P45+Q45)-(MIN(N45,N($E$9))+MIN(O45,N($E$10))))) -> 160 | S45: =MAX(0,MIN(N45,$C$14-(P45+Q45+R45)-(MIN(O45,N($E$10))))) -> 0 | T45: =MAX(0,MIN(O45,$C$14-(P45+Q45+R45+S45)-(0))) -> 0 | U45: =ROUND(K45-P45,2) -> 2244.56 | V45: =ROUND(L45-Q45,2) -> 7416.91 | W45: =ROUND(M45-R45,2) -> 13997.93 | X45: =ROUND(N45-S45,2) -> 0 | Y45: =ROUND(O45-T45,2) -> 0 | Z45: =SUM(U45:Y45) -> 23659.4
J46: =EDATE($C$13,5) -> 46539 | K46: =U45*(1+N($D$6)/12) -> 2287.3937 | L46: =V45*(1+N($D$7)/12) -> 7457.0849 | M46: =W45*(1+N($D$8)/12) -> 14056.255 | N46: =X45*(1+N($D$9)/12) -> 0 | O46: =Y45*(1+N($D$10)/12) -> 0 | P46: =MAX(0,MIN(K46,$C$14-(0)-(MIN(L46,N($E$7))+MIN(M46,N($E$8))+MIN(N46,N($E$9))+MIN(O46,N($E$10))))) -> 245 | Q46: =MAX(0,MIN(L46,$C$14-(P46)-(MIN(M46,N($E$8))+MIN(N46,N($E$9))+MIN(O46,N($E$10))))) -> 240 | R46: =MAX(0,MIN(M46,$C$14-(P46+Q46)-(MIN(N46,N($E$9))+MIN(O46,N($E$10))))) -> 160 | S46: =MAX(0,MIN(N46,$C$14-(P46+Q46+R46)-(MIN(O46,N($E$10))))) -> 0 | T46: =MAX(0,MIN(O46,$C$14-(P46+Q46+R46+S46)-(0))) -> 0 | U46: =ROUND(K46-P46,2) -> 2042.39 | V46: =ROUND(L46-Q46,2) -> 7217.08 | W46: =ROUND(M46-R46,2) -> 13896.25 | X46: =ROUND(N46-S46,2) -> 0 | Y46: =ROUND(O46-T46,2) -> 0 | Z46: =SUM(U46:Y46) -> 23155.72
J47: =EDATE($C$13,6) -> 46569 | K47: =U46*(1+N($D$6)/12) -> 2081.3656 | L47: =V46*(1+N($D$7)/12) -> 7256.1725 | M47: =W46*(1+N($D$8)/12) -> 13954.151 | N47: =X46*(1+N($D$9)/12) -> 0 | O47: =Y46*(1+N($D$10)/12) -> 0 | P47: =MAX(0,MIN(K47,$C$14-(0)-(MIN(L47,N($E$7))+MIN(M47,N($E$8))+MIN(N47,N($E$9))+MIN(O47,N($E$10))))) -> 245 | Q47: =MAX(0,MIN(L47,$C$14-(P47)-(MIN(M47,N($E$8))+MIN(N47,N($E$9))+MIN(O47,N($E$10))))) -> 240 | R47: =MAX(0,MIN(M47,$C$14-(P47+Q47)-(MIN(N47,N($E$9))+MIN(O47,N($E$10))))) -> 160 | S47: =MAX(0,MIN(N47,$C$14-(P47+Q47+R47)-(MIN(O47,N($E$10))))) -> 0 | T47: =MAX(0,MIN(O47,$C$14-(P47+Q47+R47+S47)-(0))) -> 0 | U47: =ROUND(K47-P47,2) -> 1836.37 | V47: =ROUND(L47-Q47,2) -> 7016.17 | W47: =ROUND(M47-R47,2) -> 13794.15 | X47: =ROUND(N47-S47,2) -> 0 | Y47: =ROUND(O47-T47,2) -> 0 | Z47: =SUM(U47:Y47) -> 22646.69
J48: =EDATE($C$13,7) -> 46600 | K48: =U47*(1+N($D$6)/12) -> 1871.4141 | L48: =V47*(1+N($D$7)/12) -> 7054.1743 | M48: =W47*(1+N($D$8)/12) -> 13851.626 | N48: =X47*(1+N($D$9)/12) -> 0 | O48: =Y47*(1+N($D$10)/12) -> 0 | P48: =MAX(0,MIN(K48,$C$14-(0)-(MIN(L48,N($E$7))+MIN(M48,N($E$8))+MIN(N48,N($E$9))+MIN(O48,N($E$10))))) -> 245 | Q48: =MAX(0,MIN(L48,$C$14-(P48)-(MIN(M48,N($E$8))+MIN(N48,N($E$9))+MIN(O48,N($E$10))))) -> 240 | R48: =MAX(0,MIN(M48,$C$14-(P48+Q48)-(MIN(N48,N($E$9))+MIN(O48,N($E$10))))) -> 160 | S48: =MAX(0,MIN(N48,$C$14-(P48+Q48+R48)-(MIN(O48,N($E$10))))) -> 0 | T48: =MAX(0,MIN(O48,$C$14-(P48+Q48+R48+S48)-(0))) -> 0 | U48: =ROUND(K48-P48,2) -> 1626.41 | V48: =ROUND(L48-Q48,2) -> 6814.17 | W48: =ROUND(M48-R48,2) -> 13691.63 | X48: =ROUND(N48-S48,2) -> 0 | Y48: =ROUND(O48-T48,2) -> 0 | Z48: =SUM(U48:Y48) -> 22132.21
J49: =EDATE($C$13,8) -> 46631 | K49: =U48*(1+N($D$6)/12) -> 1657.4473 | L49: =V48*(1+N($D$7)/12) -> 6851.0801 | M49: =W48*(1+N($D$8)/12) -> 13748.678 | N49: =X48*(1+N($D$9)/12) -> 0 | O49: =Y48*(1+N($D$10)/12) -> 0 | P49: =MAX(0,MIN(K49,$C$14-(0)-(MIN(L49,N($E$7))+MIN(M49,N($E$8))+MIN(N49,N($E$9))+MIN(O49,N($E$10))))) -> 245 | Q49: =MAX(0,MIN(L49,$C$14-(P49)-(MIN(M49,N($E$8))+MIN(N49,N($E$9))+MIN(O49,N($E$10))))) -> 240 | R49: =MAX(0,MIN(M49,$C$14-(P49+Q49)-(MIN(N49,N($E$9))+MIN(O49,N($E$10))))) -> 160 | S49: =MAX(0,MIN(N49,$C$14-(P49+Q49+R49)-(MIN(O49,N($E$10))))) -> 0 | T49: =MAX(0,MIN(O49,$C$14-(P49+Q49+R49+S49)-(0))) -> 0 | U49: =ROUND(K49-P49,2) -> 1412.45 | V49: =ROUND(L49-Q49,2) -> 6611.08 | W49: =ROUND(M49-R49,2) -> 13588.68 | X49: =ROUND(N49-S49,2) -> 0 | Y49: =ROUND(O49-T49,2) -> 0 | Z49: =SUM(U49:Y49) -> 21612.21
J50: =EDATE($C$13,9) -> 46661 | K50: =U49*(1+N($D$6)/12) -> 1439.4043 | L50: =V49*(1+N($D$7)/12) -> 6646.89 | M50: =W49*(1+N($D$8)/12) -> 13645.299 | N50: =X49*(1+N($D$9)/12) -> 0 | O50: =Y49*(1+N($D$10)/12) -> 0 | P50: =MAX(0,MIN(K50,$C$14-(0)-(MIN(L50,N($E$7))+MIN(M50,N($E$8))+MIN(N50,N($E$9))+MIN(O50,N($E$10))))) -> 245 | Q50: =MAX(0,MIN(L50,$C$14-(P50)-(MIN(M50,N($E$8))+MIN(N50,N($E$9))+MIN(O50,N($E$10))))) -> 240 | R50: =MAX(0,MIN(M50,$C$14-(P50+Q50)-(MIN(N50,N($E$9))+MIN(O50,N($E$10))))) -> 160 | S50: =MAX(0,MIN(N50,$C$14-(P50+Q50+R50)-(MIN(O50,N($E$10))))) -> 0 | T50: =MAX(0,MIN(O50,$C$14-(P50+Q50+R50+S50)-(0))) -> 0 | U50: =ROUND(K50-P50,2) -> 1194.4 | V50: =ROUND(L50-Q50,2) -> 6406.89 | W50: =ROUND(M50-R50,2) -> 13485.3 | X50: =ROUND(N50-S50,2) -> 0 | Y50: =ROUND(O50-T50,2) -> 0 | Z50: =SUM(U50:Y50) -> 21086.59
J51: =EDATE($C$13,10) -> 46692 | K51: =U50*(1+N($D$6)/12) -> 1217.1931 | L51: =V50*(1+N($D$7)/12) -> 6441.594 | M51: =W50*(1+N($D$8)/12) -> 13541.489 | N51: =X50*(1+N($D$9)/12) -> 0 | O51: =Y50*(1+N($D$10)/12) -> 0 | P51: =MAX(0,MIN(K51,$C$14-(0)-(MIN(L51,N($E$7))+MIN(M51,N($E$8))+MIN(N51,N($E$9))+MIN(O51,N($E$10))))) -> 245 | Q51: =MAX(0,MIN(L51,$C$14-(P51)-(MIN(M51,N($E$8))+MIN(N51,N($E$9))+MIN(O51,N($E$10))))) -> 240 | R51: =MAX(0,MIN(M51,$C$14-(P51+Q51)-(MIN(N51,N($E$9))+MIN(O51,N($E$10))))) -> 160 | S51: =MAX(0,MIN(N51,$C$14-(P51+Q51+R51)-(MIN(O51,N($E$10))))) -> 0 | T51: =MAX(0,MIN(O51,$C$14-(P51+Q51+R51+S51)-(0))) -> 0 | U51: =ROUND(K51-P51,2) -> 972.19 | V51: =ROUND(L51-Q51,2) -> 6201.59 | W51: =ROUND(M51-R51,2) -> 13381.49 | X51: =ROUND(N51-S51,2) -> 0 | Y51: =ROUND(O51-T51,2) -> 0 | Z51: =SUM(U51:Y51) -> 20555.27
J52: =EDATE($C$13,11) -> 46722 | K52: =U51*(1+N($D$6)/12) -> 990.74263 | L52: =V51*(1+N($D$7)/12) -> 6235.1819 | M52: =W51*(1+N($D$8)/12) -> 13437.246 | N52: =X51*(1+N($D$9)/12) -> 0 | O52: =Y51*(1+N($D$10)/12) -> 0 | P52: =MAX(0,MIN(K52,$C$14-(0)-(MIN(L52,N($E$7))+MIN(M52,N($E$8))+MIN(N52,N($E$9))+MIN(O52,N($E$10))))) -> 245 | Q52: =MAX(0,MIN(L52,$C$14-(P52)-(MIN(M52,N($E$8))+MIN(N52,N($E$9))+MIN(O52,N($E$10))))) -> 240 | R52: =MAX(0,MIN(M52,$C$14-(P52+Q52)-(MIN(N52,N($E$9))+MIN(O52,N($E$10))))) -> 160 | S52: =MAX(0,MIN(N52,$C$14-(P52+Q52+R52)-(MIN(O52,N($E$10))))) -> 0 | T52: =MAX(0,MIN(O52,$C$14-(P52+Q52+R52+S52)-(0))) -> 0 | U52: =ROUND(K52-P52,2) -> 745.74 | V52: =ROUND(L52-Q52,2) -> 5995.18 | W52: =ROUND(M52-R52,2) -> 13277.25 | X52: =ROUND(N52-S52,2) -> 0 | Y52: =ROUND(O52-T52,2) -> 0 | Z52: =SUM(U52:Y52) -> 20018.17
J53: =EDATE($C$13,12) -> 46753 | K53: =U52*(1+N($D$6)/12) -> 759.97121 | L53: =V52*(1+N($D$7)/12) -> 6027.6539 | M53: =W52*(1+N($D$8)/12) -> 13332.572 | N53: =X52*(1+N($D$9)/12) -> 0 | O53: =Y52*(1+N($D$10)/12) -> 0 | P53: =MAX(0,MIN(K53,$C$14-(0)-(MIN(L53,N($E$7))+MIN(M53,N($E$8))+MIN(N53,N($E$9))+MIN(O53,N($E$10))))) -> 245 | Q53: =MAX(0,MIN(L53,$C$14-(P53)-(MIN(M53,N($E$8))+MIN(N53,N($E$9))+MIN(O53,N($E$10))))) -> 240 | R53: =MAX(0,MIN(M53,$C$14-(P53+Q53)-(MIN(N53,N($E$9))+MIN(O53,N($E$10))))) -> 160 | S53: =MAX(0,MIN(N53,$C$14-(P53+Q53+R53)-(MIN(O53,N($E$10))))) -> 0 | T53: =MAX(0,MIN(O53,$C$14-(P53+Q53+R53+S53)-(0))) -> 0 | U53: =ROUND(K53-P53,2) -> 514.97 | V53: =ROUND(L53-Q53,2) -> 5787.65 | W53: =ROUND(M53-R53,2) -> 13172.57 | X53: =ROUND(N53-S53,2) -> 0 | Y53: =ROUND(O53-T53,2) -> 0 | Z53: =SUM(U53:Y53) -> 19475.19
J54: =EDATE($C$13,13) -> 46784 | K54: =U53*(1+N($D$6)/12) -> 524.79734 | L54: =V53*(1+N($D$7)/12) -> 5818.9998 | M54: =W53*(1+N($D$8)/12) -> 13227.456 | N54: =X53*(1+N($D$9)/12) -> 0 | O54: =Y53*(1+N($D$10)/12) -> 0 | P54: =MAX(0,MIN(K54,$C$14-(0)-(MIN(L54,N($E$7))+MIN(M54,N($E$8))+MIN(N54,N($E$9))+MIN(O54,N($E$10))))) -> 245 | Q54: =MAX(0,MIN(L54,$C$14-(P54)-(MIN(M54,N($E$8))+MIN(N54,N($E$9))+MIN(O54,N($E$10))))) -> 240 | R54: =MAX(0,MIN(M54,$C$14-(P54+Q54)-(MIN(N54,N($E$9))+MIN(O54,N($E$10))))) -> 160 | S54: =MAX(0,MIN(N54,$C$14-(P54+Q54+R54)-(MIN(O54,N($E$10))))) -> 0 | T54: =MAX(0,MIN(O54,$C$14-(P54+Q54+R54+S54)-(0))) -> 0 | U54: =ROUND(K54-P54,2) -> 279.8 | V54: =ROUND(L54-Q54,2) -> 5579 | W54: =ROUND(M54-R54,2) -> 13067.46 | X54: =ROUND(N54-S54,2) -> 0 | Y54: =ROUND(O54-T54,2) -> 0 | Z54: =SUM(U54:Y54) -> 18926.26
J55: =EDATE($C$13,14) -> 46813 | K55: =U54*(1+N($D$6)/12) -> 285.13952 | L55: =V54*(1+N($D$7)/12) -> 5609.2196 | M55: =W54*(1+N($D$8)/12) -> 13121.908 | N55: =X54*(1+N($D$9)/12) -> 0 | O55: =Y54*(1+N($D$10)/12) -> 0 | P55: =MAX(0,MIN(K55,$C$14-(0)-(MIN(L55,N($E$7))+MIN(M55,N($E$8))+MIN(N55,N($E$9))+MIN(O55,N($E$10))))) -> 245 | Q55: =MAX(0,MIN(L55,$C$14-(P55)-(MIN(M55,N($E$8))+MIN(N55,N($E$9))+MIN(O55,N($E$10))))) -> 240 | R55: =MAX(0,MIN(M55,$C$14-(P55+Q55)-(MIN(N55,N($E$9))+MIN(O55,N($E$10))))) -> 160 | S55: =MAX(0,MIN(N55,$C$14-(P55+Q55+R55)-(MIN(O55,N($E$10))))) -> 0 | T55: =MAX(0,MIN(O55,$C$14-(P55+Q55+R55+S55)-(0))) -> 0 | U55: =ROUND(K55-P55,2) -> 40.14 | V55: =ROUND(L55-Q55,2) -> 5369.22 | W55: =ROUND(M55-R55,2) -> 12961.91 | X55: =ROUND(N55-S55,2) -> 0 | Y55: =ROUND(O55-T55,2) -> 0 | Z55: =SUM(U55:Y55) -> 18371.27
J56: =EDATE($C$13,15) -> 46844 | K56: =U55*(1+N($D$6)/12) -> 40.906005 | L56: =V55*(1+N($D$7)/12) -> 5398.3033 | M56: =W55*(1+N($D$8)/12) -> 13015.918 | N56: =X55*(1+N($D$9)/12) -> 0 | O56: =Y55*(1+N($D$10)/12) -> 0 | P56: =MAX(0,MIN(K56,$C$14-(0)-(MIN(L56,N($E$7))+MIN(M56,N($E$8))+MIN(N56,N($E$9))+MIN(O56,N($E$10))))) -> 40.906005 | Q56: =MAX(0,MIN(L56,$C$14-(P56)-(MIN(M56,N($E$8))+MIN(N56,N($E$9))+MIN(O56,N($E$10))))) -> 444.094 | R56: =MAX(0,MIN(M56,$C$14-(P56+Q56)-(MIN(N56,N($E$9))+MIN(O56,N($E$10))))) -> 160 | S56: =MAX(0,MIN(N56,$C$14-(P56+Q56+R56)-(MIN(O56,N($E$10))))) -> 0 | T56: =MAX(0,MIN(O56,$C$14-(P56+Q56+R56+S56)-(0))) -> 0 | U56: =ROUND(K56-P56,2) -> 0 | V56: =ROUND(L56-Q56,2) -> 4954.21 | W56: =ROUND(M56-R56,2) -> 12855.92 | X56: =ROUND(N56-S56,2) -> 0 | Y56: =ROUND(O56-T56,2) -> 0 | Z56: =SUM(U56:Y56) -> 17810.13
J57: =EDATE($C$13,16) -> 46874 | K57: =U56*(1+N($D$6)/12) -> 0 | L57: =V56*(1+N($D$7)/12) -> 4981.0453 | M57: =W56*(1+N($D$8)/12) -> 12909.486 | N57: =X56*(1+N($D$9)/12) -> 0 | O57: =Y56*(1+N($D$10)/12) -> 0 | P57: =MAX(0,MIN(K57,$C$14-(0)-(MIN(L57,N($E$7))+MIN(M57,N($E$8))+MIN(N57,N($E$9))+MIN(O57,N($E$10))))) -> 0 | Q57: =MAX(0,MIN(L57,$C$14-(P57)-(MIN(M57,N($E$8))+MIN(N57,N($E$9))+MIN(O57,N($E$10))))) -> 485 | R57: =MAX(0,MIN(M57,$C$14-(P57+Q57)-(MIN(N57,N($E$9))+MIN(O57,N($E$10))))) -> 160 | S57: =MAX(0,MIN(N57,$C$14-(P57+Q57+R57)-(MIN(O57,N($E$10))))) -> 0 | T57: =MAX(0,MIN(O57,$C$14-(P57+Q57+R57+S57)-(0))) -> 0 | U57: =ROUND(K57-P57,2) -> 0 | V57: =ROUND(L57-Q57,2) -> 4496.05 | W57: =ROUND(M57-R57,2) -> 12749.49 | X57: =ROUND(N57-S57,2) -> 0 | Y57: =ROUND(O57-T57,2) -> 0 | Z57: =SUM(U57:Y57) -> 17245.54
J58: =EDATE($C$13,17) -> 46905 | K58: =U57*(1+N($D$6)/12) -> 0 | L58: =V57*(1+N($D$7)/12) -> 4520.4036 | M58: =W57*(1+N($D$8)/12) -> 12802.613 | N58: =X57*(1+N($D$9)/12) -> 0 | O58: =Y57*(1+N($D$10)/12) -> 0 | P58: =MAX(0,MIN(K58,$C$14-(0)-(MIN(L58,N($E$7))+MIN(M58,N($E$8))+MIN(N58,N($E$9))+MIN(O58,N($E$10))))) -> 0 | Q58: =MAX(0,MIN(L58,$C$14-(P58)-(MIN(M58,N($E$8))+MIN(N58,N($E$9))+MIN(O58,N($E$10))))) -> 485 | R58: =MAX(0,MIN(M58,$C$14-(P58+Q58)-(MIN(N58,N($E$9))+MIN(O58,N($E$10))))) -> 160 | S58: =MAX(0,MIN(N58,$C$14-(P58+Q58+R58)-(MIN(O58,N($E$10))))) -> 0 | T58: =MAX(0,MIN(O58,$C$14-(P58+Q58+R58+S58)-(0))) -> 0 | U58: =ROUND(K58-P58,2) -> 0 | V58: =ROUND(L58-Q58,2) -> 4035.4 | W58: =ROUND(M58-R58,2) -> 12642.61 | X58: =ROUND(N58-S58,2) -> 0 | Y58: =ROUND(O58-T58,2) -> 0 | Z58: =SUM(U58:Y58) -> 16678.01
J59: =EDATE($C$13,18) -> 46935 | K59: =U58*(1+N($D$6)/12) -> 0 | L59: =V58*(1+N($D$7)/12) -> 4057.2584 | M59: =W58*(1+N($D$8)/12) -> 12695.288 | N59: =X58*(1+N($D$9)/12) -> 0 | O59: =Y58*(1+N($D$10)/12) -> 0 | P59: =MAX(0,MIN(K59,$C$14-(0)-(MIN(L59,N($E$7))+MIN(M59,N($E$8))+MIN(N59,N($E$9))+MIN(O59,N($E$10))))) -> 0 | Q59: =MAX(0,MIN(L59,$C$14-(P59)-(MIN(M59,N($E$8))+MIN(N59,N($E$9))+MIN(O59,N($E$10))))) -> 485 | R59: =MAX(0,MIN(M59,$C$14-(P59+Q59)-(MIN(N59,N($E$9))+MIN(O59,N($E$10))))) -> 160 | S59: =MAX(0,MIN(N59,$C$14-(P59+Q59+R59)-(MIN(O59,N($E$10))))) -> 0 | T59: =MAX(0,MIN(O59,$C$14-(P59+Q59+R59+S59)-(0))) -> 0 | U59: =ROUND(K59-P59,2) -> 0 | V59: =ROUND(L59-Q59,2) -> 3572.26 | W59: =ROUND(M59-R59,2) -> 12535.29 | X59: =ROUND(N59-S59,2) -> 0 | Y59: =ROUND(O59-T59,2) -> 0 | Z59: =SUM(U59:Y59) -> 16107.55
J60: =EDATE($C$13,19) -> 46966 | K60: =U59*(1+N($D$6)/12) -> 0 | L60: =V59*(1+N($D$7)/12) -> 3591.6097 | M60: =W59*(1+N($D$8)/12) -> 12587.52 | N60: =X59*(1+N($D$9)/12) -> 0 | O60: =Y59*(1+N($D$10)/12) -> 0 | P60: =MAX(0,MIN(K60,$C$14-(0)-(MIN(L60,N($E$7))+MIN(M60,N($E$8))+MIN(N60,N($E$9))+MIN(O60,N($E$10))))) -> 0 | Q60: =MAX(0,MIN(L60,$C$14-(P60)-(MIN(M60,N($E$8))+MIN(N60,N($E$9))+MIN(O60,N($E$10))))) -> 485 | R60: =MAX(0,MIN(M60,$C$14-(P60+Q60)-(MIN(N60,N($E$9))+MIN(O60,N($E$10))))) -> 160 | S60: =MAX(0,MIN(N60,$C$14-(P60+Q60+R60)-(MIN(O60,N($E$10))))) -> 0 | T60: =MAX(0,MIN(O60,$C$14-(P60+Q60+R60+S60)-(0))) -> 0 | U60: =ROUND(K60-P60,2) -> 0 | V60: =ROUND(L60-Q60,2) -> 3106.61 | W60: =ROUND(M60-R60,2) -> 12427.52 | X60: =ROUND(N60-S60,2) -> 0 | Y60: =ROUND(O60-T60,2) -> 0 | Z60: =SUM(U60:Y60) -> 15534.13
J61: =EDATE($C$13,20) -> 46997 | K61: =U60*(1+N($D$6)/12) -> 0 | L61: =V60*(1+N($D$7)/12) -> 3123.4375 | M61: =W60*(1+N($D$8)/12) -> 12479.301 | N61: =X60*(1+N($D$9)/12) -> 0 | O61: =Y60*(1+N($D$10)/12) -> 0 | P61: =MAX(0,MIN(K61,$C$14-(0)-(MIN(L61,N($E$7))+MIN(M61,N($E$8))+MIN(N61,N($E$9))+MIN(O61,N($E$10))))) -> 0 | Q61: =MAX(0,MIN(L61,$C$14-(P61)-(MIN(M61,N($E$8))+MIN(N61,N($E$9))+MIN(O61,N($E$10))))) -> 485 | R61: =MAX(0,MIN(M61,$C$14-(P61+Q61)-(MIN(N61,N($E$9))+MIN(O61,N($E$10))))) -> 160 | S61: =MAX(0,MIN(N61,$C$14-(P61+Q61+R61)-(MIN(O61,N($E$10))))) -> 0 | T61: =MAX(0,MIN(O61,$C$14-(P61+Q61+R61+S61)-(0))) -> 0 | U61: =ROUND(K61-P61,2) -> 0 | V61: =ROUND(L61-Q61,2) -> 2638.44 | W61: =ROUND(M61-R61,2) -> 12319.3 | X61: =ROUND(N61-S61,2) -> 0 | Y61: =ROUND(O61-T61,2) -> 0 | Z61: =SUM(U61:Y61) -> 14957.74
J62: =EDATE($C$13,21) -> 47027 | K62: =U61*(1+N($D$6)/12) -> 0 | L62: =V61*(1+N($D$7)/12) -> 2652.7315 | M62: =W61*(1+N($D$8)/12) -> 12370.63 | N62: =X61*(1+N($D$9)/12) -> 0 | O62: =Y61*(1+N($D$10)/12) -> 0 | P62: =MAX(0,MIN(K62,$C$14-(0)-(MIN(L62,N($E$7))+MIN(M62,N($E$8))+MIN(N62,N($E$9))+MIN(O62,N($E$10))))) -> 0 | Q62: =MAX(0,MIN(L62,$C$14-(P62)-(MIN(M62,N($E$8))+MIN(N62,N($E$9))+MIN(O62,N($E$10))))) -> 485 | R62: =MAX(0,MIN(M62,$C$14-(P62+Q62)-(MIN(N62,N($E$9))+MIN(O62,N($E$10))))) -> 160 | S62: =MAX(0,MIN(N62,$C$14-(P62+Q62+R62)-(MIN(O62,N($E$10))))) -> 0 | T62: =MAX(0,MIN(O62,$C$14-(P62+Q62+R62+S62)-(0))) -> 0 | U62: =ROUND(K62-P62,2) -> 0 | V62: =ROUND(L62-Q62,2) -> 2167.73 | W62: =ROUND(M62-R62,2) -> 12210.63 | X62: =ROUND(N62-S62,2) -> 0 | Y62: =ROUND(O62-T62,2) -> 0 | Z62: =SUM(U62:Y62) -> 14378.36
J63: =EDATE($C$13,22) -> 47058 | K63: =U62*(1+N($D$6)/12) -> 0 | L63: =V62*(1+N($D$7)/12) -> 2179.4719 | M63: =W62*(1+N($D$8)/12) -> 12261.508 | N63: =X62*(1+N($D$9)/12) -> 0 | O63: =Y62*(1+N($D$10)/12) -> 0 | P63: =MAX(0,MIN(K63,$C$14-(0)-(MIN(L63,N($E$7))+MIN(M63,N($E$8))+MIN(N63,N($E$9))+MIN(O63,N($E$10))))) -> 0 | Q63: =MAX(0,MIN(L63,$C$14-(P63)-(MIN(M63,N($E$8))+MIN(N63,N($E$9))+MIN(O63,N($E$10))))) -> 485 | R63: =MAX(0,MIN(M63,$C$14-(P63+Q63)-(MIN(N63,N($E$9))+MIN(O63,N($E$10))))) -> 160 | S63: =MAX(0,MIN(N63,$C$14-(P63+Q63+R63)-(MIN(O63,N($E$10))))) -> 0 | T63: =MAX(0,MIN(O63,$C$14-(P63+Q63+R63+S63)-(0))) -> 0 | U63: =ROUND(K63-P63,2) -> 0 | V63: =ROUND(L63-Q63,2) -> 1694.47 | W63: =ROUND(M63-R63,2) -> 12101.51 | X63: =ROUND(N63-S63,2) -> 0 | Y63: =ROUND(O63-T63,2) -> 0 | Z63: =SUM(U63:Y63) -> 13795.98
J64: =EDATE($C$13,23) -> 47088 | K64: =U63*(1+N($D$6)/12) -> 0 | L64: =V63*(1+N($D$7)/12) -> 1703.6484 | M64: =W63*(1+N($D$8)/12) -> 12151.933 | N64: =X63*(1+N($D$9)/12) -> 0 | O64: =Y63*(1+N($D$10)/12) -> 0 | P64: =MAX(0,MIN(K64,$C$14-(0)-(MIN(L64,N($E$7))+MIN(M64,N($E$8))+MIN(N64,N($E$9))+MIN(O64,N($E$10))))) -> 0 | Q64: =MAX(0,MIN(L64,$C$14-(P64)-(MIN(M64,N($E$8))+MIN(N64,N($E$9))+MIN(O64,N($E$10))))) -> 485 | R64: =MAX(0,MIN(M64,$C$14-(P64+Q64)-(MIN(N64,N($E$9))+MIN(O64,N($E$10))))) -> 160 | S64: =MAX(0,MIN(N64,$C$14-(P64+Q64+R64)-(MIN(O64,N($E$10))))) -> 0 | T64: =MAX(0,MIN(O64,$C$14-(P64+Q64+R64+S64)-(0))) -> 0 | U64: =ROUND(K64-P64,2) -> 0 | V64: =ROUND(L64-Q64,2) -> 1218.65 | W64: =ROUND(M64-R64,2) -> 11991.93 | X64: =ROUND(N64-S64,2) -> 0 | Y64: =ROUND(O64-T64,2) -> 0 | Z64: =SUM(U64:Y64) -> 13210.58
J65: =EDATE($C$13,24) -> 47119 | K65: =U64*(1+N($D$6)/12) -> 0 | L65: =V64*(1+N($D$7)/12) -> 1225.251 | M65: =W64*(1+N($D$8)/12) -> 12041.896 | N65: =X64*(1+N($D$9)/12) -> 0 | O65: =Y64*(1+N($D$10)/12) -> 0 | P65: =MAX(0,MIN(K65,$C$14-(0)-(MIN(L65,N($E$7))+MIN(M65,N($E$8))+MIN(N65,N($E$9))+MIN(O65,N($E$10))))) -> 0 | Q65: =MAX(0,MIN(L65,$C$14-(P65)-(MIN(M65,N($E$8))+MIN(N65,N($E$9))+MIN(O65,N($E$10))))) -> 485 | R65: =MAX(0,MIN(M65,$C$14-(P65+Q65)-(MIN(N65,N($E$9))+MIN(O65,N($E$10))))) -> 160 | S65: =MAX(0,MIN(N65,$C$14-(P65+Q65+R65)-(MIN(O65,N($E$10))))) -> 0 | T65: =MAX(0,MIN(O65,$C$14-(P65+Q65+R65+S65)-(0))) -> 0 | U65: =ROUND(K65-P65,2) -> 0 | V65: =ROUND(L65-Q65,2) -> 740.25 | W65: =ROUND(M65-R65,2) -> 11881.9 | X65: =ROUND(N65-S65,2) -> 0 | Y65: =ROUND(O65-T65,2) -> 0 | Z65: =SUM(U65:Y65) -> 12622.15
J66: =EDATE($C$13,25) -> 47150 | K66: =U65*(1+N($D$6)/12) -> 0 | L66: =V65*(1+N($D$7)/12) -> 744.25969 | M66: =W65*(1+N($D$8)/12) -> 11931.408 | N66: =X65*(1+N($D$9)/12) -> 0 | O66: =Y65*(1+N($D$10)/12) -> 0 | P66: =MAX(0,MIN(K66,$C$14-(0)-(MIN(L66,N($E$7))+MIN(M66,N($E$8))+MIN(N66,N($E$9))+MIN(O66,N($E$10))))) -> 0 | Q66: =MAX(0,MIN(L66,$C$14-(P66)-(MIN(M66,N($E$8))+MIN(N66,N($E$9))+MIN(O66,N($E$10))))) -> 485 | R66: =MAX(0,MIN(M66,$C$14-(P66+Q66)-(MIN(N66,N($E$9))+MIN(O66,N($E$10))))) -> 160 | S66: =MAX(0,MIN(N66,$C$14-(P66+Q66+R66)-(MIN(O66,N($E$10))))) -> 0 | T66: =MAX(0,MIN(O66,$C$14-(P66+Q66+R66+S66)-(0))) -> 0 | U66: =ROUND(K66-P66,2) -> 0 | V66: =ROUND(L66-Q66,2) -> 259.26 | W66: =ROUND(M66-R66,2) -> 11771.41 | X66: =ROUND(N66-S66,2) -> 0 | Y66: =ROUND(O66-T66,2) -> 0 | Z66: =SUM(U66:Y66) -> 12030.67
J67: =EDATE($C$13,26) -> 47178 | K67: =U66*(1+N($D$6)/12) -> 0 | L67: =V66*(1+N($D$7)/12) -> 260.66433 | M67: =W66*(1+N($D$8)/12) -> 11820.458 | N67: =X66*(1+N($D$9)/12) -> 0 | O67: =Y66*(1+N($D$10)/12) -> 0 | P67: =MAX(0,MIN(K67,$C$14-(0)-(MIN(L67,N($E$7))+MIN(M67,N($E$8))+MIN(N67,N($E$9))+MIN(O67,N($E$10))))) -> 0 | Q67: =MAX(0,MIN(L67,$C$14-(P67)-(MIN(M67,N($E$8))+MIN(N67,N($E$9))+MIN(O67,N($E$10))))) -> 260.66433 | R67: =MAX(0,MIN(M67,$C$14-(P67+Q67)-(MIN(N67,N($E$9))+MIN(O67,N($E$10))))) -> 384.33567 | S67: =MAX(0,MIN(N67,$C$14-(P67+Q67+R67)-(MIN(O67,N($E$10))))) -> 0 | T67: =MAX(0,MIN(O67,$C$14-(P67+Q67+R67+S67)-(0))) -> 0 | U67: =ROUND(K67-P67,2) -> 0 | V67: =ROUND(L67-Q67,2) -> 0 | W67: =ROUND(M67-R67,2) -> 11436.12 | X67: =ROUND(N67-S67,2) -> 0 | Y67: =ROUND(O67-T67,2) -> 0 | Z67: =SUM(U67:Y67) -> 11436.12
J68: =EDATE($C$13,27) -> 47209 | K68: =U67*(1+N($D$6)/12) -> 0 | L68: =V67*(1+N($D$7)/12) -> 0 | M68: =W67*(1+N($D$8)/12) -> 11483.771 | N68: =X67*(1+N($D$9)/12) -> 0 | O68: =Y67*(1+N($D$10)/12) -> 0 | P68: =MAX(0,MIN(K68,$C$14-(0)-(MIN(L68,N($E$7))+MIN(M68,N($E$8))+MIN(N68,N($E$9))+MIN(O68,N($E$10))))) -> 0 | Q68: =MAX(0,MIN(L68,$C$14-(P68)-(MIN(M68,N($E$8))+MIN(N68,N($E$9))+MIN(O68,N($E$10))))) -> 0 | R68: =MAX(0,MIN(M68,$C$14-(P68+Q68)-(MIN(N68,N($E$9))+MIN(O68,N($E$10))))) -> 645 | S68: =MAX(0,MIN(N68,$C$14-(P68+Q68+R68)-(MIN(O68,N($E$10))))) -> 0 | T68: =MAX(0,MIN(O68,$C$14-(P68+Q68+R68+S68)-(0))) -> 0 | U68: =ROUND(K68-P68,2) -> 0 | V68: =ROUND(L68-Q68,2) -> 0 | W68: =ROUND(M68-R68,2) -> 10838.77 | X68: =ROUND(N68-S68,2) -> 0 | Y68: =ROUND(O68-T68,2) -> 0 | Z68: =SUM(U68:Y68) -> 10838.77
J69: =EDATE($C$13,28) -> 47239 | K69: =U68*(1+N($D$6)/12) -> 0 | L69: =V68*(1+N($D$7)/12) -> 0 | M69: =W68*(1+N($D$8)/12) -> 10883.932 | N69: =X68*(1+N($D$9)/12) -> 0 | O69: =Y68*(1+N($D$10)/12) -> 0 | P69: =MAX(0,MIN(K69,$C$14-(0)-(MIN(L69,N($E$7))+MIN(M69,N($E$8))+MIN(N69,N($E$9))+MIN(O69,N($E$10))))) -> 0 | Q69: =MAX(0,MIN(L69,$C$14-(P69)-(MIN(M69,N($E$8))+MIN(N69,N($E$9))+MIN(O69,N($E$10))))) -> 0 | R69: =MAX(0,MIN(M69,$C$14-(P69+Q69)-(MIN(N69,N($E$9))+MIN(O69,N($E$10))))) -> 645 | S69: =MAX(0,MIN(N69,$C$14-(P69+Q69+R69)-(MIN(O69,N($E$10))))) -> 0 | T69: =MAX(0,MIN(O69,$C$14-(P69+Q69+R69+S69)-(0))) -> 0 | U69: =ROUND(K69-P69,2) -> 0 | V69: =ROUND(L69-Q69,2) -> 0 | W69: =ROUND(M69-R69,2) -> 10238.93 | X69: =ROUND(N69-S69,2) -> 0 | Y69: =ROUND(O69-T69,2) -> 0 | Z69: =SUM(U69:Y69) -> 10238.93
J70: =EDATE($C$13,29) -> 47270 | K70: =U69*(1+N($D$6)/12) -> 0 | L70: =V69*(1+N($D$7)/12) -> 0 | M70: =W69*(1+N($D$8)/12) -> 10281.592 | N70: =X69*(1+N($D$9)/12) -> 0 | O70: =Y69*(1+N($D$10)/12) -> 0 | P70: =MAX(0,MIN(K70,$C$14-(0)-(MIN(L70,N($E$7))+MIN(M70,N($E$8))+MIN(N70,N($E$9))+MIN(O70,N($E$10))))) -> 0 | Q70: =MAX(0,MIN(L70,$C$14-(P70)-(MIN(M70,N($E$8))+MIN(N70,N($E$9))+MIN(O70,N($E$10))))) -> 0 | R70: =MAX(0,MIN(M70,$C$14-(P70+Q70)-(MIN(N70,N($E$9))+MIN(O70,N($E$10))))) -> 645 | S70: =MAX(0,MIN(N70,$C$14-(P70+Q70+R70)-(MIN(O70,N($E$10))))) -> 0 | T70: =MAX(0,MIN(O70,$C$14-(P70+Q70+R70+S70)-(0))) -> 0 | U70: =ROUND(K70-P70,2) -> 0 | V70: =ROUND(L70-Q70,2) -> 0 | W70: =ROUND(M70-R70,2) -> 9636.59 | X70: =ROUND(N70-S70,2) -> 0 | Y70: =ROUND(O70-T70,2) -> 0 | Z70: =SUM(U70:Y70) -> 9636.59
J71: =EDATE($C$13,30) -> 47300 | K71: =U70*(1+N($D$6)/12) -> 0 | L71: =V70*(1+N($D$7)/12) -> 0 | M71: =W70*(1+N($D$8)/12) -> 9676.7425 | N71: =X70*(1+N($D$9)/12) -> 0 | O71: =Y70*(1+N($D$10)/12) -> 0 | P71: =MAX(0,MIN(K71,$C$14-(0)-(MIN(L71,N($E$7))+MIN(M71,N($E$8))+MIN(N71,N($E$9))+MIN(O71,N($E$10))))) -> 0 | Q71: =MAX(0,MIN(L71,$C$14-(P71)-(MIN(M71,N($E$8))+MIN(N71,N($E$9))+MIN(O71,N($E$10))))) -> 0 | R71: =MAX(0,MIN(M71,$C$14-(P71+Q71)-(MIN(N71,N($E$9))+MIN(O71,N($E$10))))) -> 645 | S71: =MAX(0,MIN(N71,$C$14-(P71+Q71+R71)-(MIN(O71,N($E$10))))) -> 0 | T71: =MAX(0,MIN(O71,$C$14-(P71+Q71+R71+S71)-(0))) -> 0 | U71: =ROUND(K71-P71,2) -> 0 | V71: =ROUND(L71-Q71,2) -> 0 | W71: =ROUND(M71-R71,2) -> 9031.74 | X71: =ROUND(N71-S71,2) -> 0 | Y71: =ROUND(O71-T71,2) -> 0 | Z71: =SUM(U71:Y71) -> 9031.74
J72: =EDATE($C$13,31) -> 47331 | K72: =U71*(1+N($D$6)/12) -> 0 | L72: =V71*(1+N($D$7)/12) -> 0 | M72: =W71*(1+N($D$8)/12) -> 9069.3723 | N72: =X71*(1+N($D$9)/12) -> 0 | O72: =Y71*(1+N($D$10)/12) -> 0 | P72: =MAX(0,MIN(K72,$C$14-(0)-(MIN(L72,N($E$7))+MIN(M72,N($E$8))+MIN(N72,N($E$9))+MIN(O72,N($E$10))))) -> 0 | Q72: =MAX(0,MIN(L72,$C$14-(P72)-(MIN(M72,N($E$8))+MIN(N72,N($E$9))+MIN(O72,N($E$10))))) -> 0 | R72: =MAX(0,MIN(M72,$C$14-(P72+Q72)-(MIN(N72,N($E$9))+MIN(O72,N($E$10))))) -> 645 | S72: =MAX(0,MIN(N72,$C$14-(P72+Q72+R72)-(MIN(O72,N($E$10))))) -> 0 | T72: =MAX(0,MIN(O72,$C$14-(P72+Q72+R72+S72)-(0))) -> 0 | U72: =ROUND(K72-P72,2) -> 0 | V72: =ROUND(L72-Q72,2) -> 0 | W72: =ROUND(M72-R72,2) -> 8424.37 | X72: =ROUND(N72-S72,2) -> 0 | Y72: =ROUND(O72-T72,2) -> 0 | Z72: =SUM(U72:Y72) -> 8424.37
J73: =EDATE($C$13,32) -> 47362 | K73: =U72*(1+N($D$6)/12) -> 0 | L73: =V72*(1+N($D$7)/12) -> 0 | M73: =W72*(1+N($D$8)/12) -> 8459.4715 | N73: =X72*(1+N($D$9)/12) -> 0 | O73: =Y72*(1+N($D$10)/12) -> 0 | P73: =MAX(0,MIN(K73,$C$14-(0)-(MIN(L73,N($E$7))+MIN(M73,N($E$8))+MIN(N73,N($E$9))+MIN(O73,N($E$10))))) -> 0 | Q73: =MAX(0,MIN(L73,$C$14-(P73)-(MIN(M73,N($E$8))+MIN(N73,N($E$9))+MIN(O73,N($E$10))))) -> 0 | R73: =MAX(0,MIN(M73,$C$14-(P73+Q73)-(MIN(N73,N($E$9))+MIN(O73,N($E$10))))) -> 645 | S73: =MAX(0,MIN(N73,$C$14-(P73+Q73+R73)-(MIN(O73,N($E$10))))) -> 0 | T73: =MAX(0,MIN(O73,$C$14-(P73+Q73+R73+S73)-(0))) -> 0 | U73: =ROUND(K73-P73,2) -> 0 | V73: =ROUND(L73-Q73,2) -> 0 | W73: =ROUND(M73-R73,2) -> 7814.47 | X73: =ROUND(N73-S73,2) -> 0 | Y73: =ROUND(O73-T73,2) -> 0 | Z73: =SUM(U73:Y73) -> 7814.47
J74: =EDATE($C$13,33) -> 47392 | K74: =U73*(1+N($D$6)/12) -> 0 | L74: =V73*(1+N($D$7)/12) -> 0 | M74: =W73*(1+N($D$8)/12) -> 7847.0303 | N74: =X73*(1+N($D$9)/12) -> 0 | O74: =Y73*(1+N($D$10)/12) -> 0 | P74: =MAX(0,MIN(K74,$C$14-(0)-(MIN(L74,N($E$7))+MIN(M74,N($E$8))+MIN(N74,N($E$9))+MIN(O74,N($E$10))))) -> 0 | Q74: =MAX(0,MIN(L74,$C$14-(P74)-(MIN(M74,N($E$8))+MIN(N74,N($E$9))+MIN(O74,N($E$10))))) -> 0 | R74: =MAX(0,MIN(M74,$C$14-(P74+Q74)-(MIN(N74,N($E$9))+MIN(O74,N($E$10))))) -> 645 | S74: =MAX(0,MIN(N74,$C$14-(P74+Q74+R74)-(MIN(O74,N($E$10))))) -> 0 | T74: =MAX(0,MIN(O74,$C$14-(P74+Q74+R74+S74)-(0))) -> 0 | U74: =ROUND(K74-P74,2) -> 0 | V74: =ROUND(L74-Q74,2) -> 0 | W74: =ROUND(M74-R74,2) -> 7202.03 | X74: =ROUND(N74-S74,2) -> 0 | Y74: =ROUND(O74-T74,2) -> 0 | Z74: =SUM(U74:Y74) -> 7202.03
J75: =EDATE($C$13,34) -> 47423 | K75: =U74*(1+N($D$6)/12) -> 0 | L75: =V74*(1+N($D$7)/12) -> 0 | M75: =W74*(1+N($D$8)/12) -> 7232.0385 | N75: =X74*(1+N($D$9)/12) -> 0 | O75: =Y74*(1+N($D$10)/12) -> 0 | P75: =MAX(0,MIN(K75,$C$14-(0)-(MIN(L75,N($E$7))+MIN(M75,N($E$8))+MIN(N75,N($E$9))+MIN(O75,N($E$10))))) -> 0 | Q75: =MAX(0,MIN(L75,$C$14-(P75)-(MIN(M75,N($E$8))+MIN(N75,N($E$9))+MIN(O75,N($E$10))))) -> 0 | R75: =MAX(0,MIN(M75,$C$14-(P75+Q75)-(MIN(N75,N($E$9))+MIN(O75,N($E$10))))) -> 645 | S75: =MAX(0,MIN(N75,$C$14-(P75+Q75+R75)-(MIN(O75,N($E$10))))) -> 0 | T75: =MAX(0,MIN(O75,$C$14-(P75+Q75+R75+S75)-(0))) -> 0 | U75: =ROUND(K75-P75,2) -> 0 | V75: =ROUND(L75-Q75,2) -> 0 | W75: =ROUND(M75-R75,2) -> 6587.04 | X75: =ROUND(N75-S75,2) -> 0 | Y75: =ROUND(O75-T75,2) -> 0 | Z75: =SUM(U75:Y75) -> 6587.04
J76: =EDATE($C$13,35) -> 47453 | K76: =U75*(1+N($D$6)/12) -> 0 | L76: =V75*(1+N($D$7)/12) -> 0 | M76: =W75*(1+N($D$8)/12) -> 6614.486 | N76: =X75*(1+N($D$9)/12) -> 0 | O76: =Y75*(1+N($D$10)/12) -> 0 | P76: =MAX(0,MIN(K76,$C$14-(0)-(MIN(L76,N($E$7))+MIN(M76,N($E$8))+MIN(N76,N($E$9))+MIN(O76,N($E$10))))) -> 0 | Q76: =MAX(0,MIN(L76,$C$14-(P76)-(MIN(M76,N($E$8))+MIN(N76,N($E$9))+MIN(O76,N($E$10))))) -> 0 | R76: =MAX(0,MIN(M76,$C$14-(P76+Q76)-(MIN(N76,N($E$9))+MIN(O76,N($E$10))))) -> 645 | S76: =MAX(0,MIN(N76,$C$14-(P76+Q76+R76)-(MIN(O76,N($E$10))))) -> 0 | T76: =MAX(0,MIN(O76,$C$14-(P76+Q76+R76+S76)-(0))) -> 0 | U76: =ROUND(K76-P76,2) -> 0 | V76: =ROUND(L76-Q76,2) -> 0 | W76: =ROUND(M76-R76,2) -> 5969.49 | X76: =ROUND(N76-S76,2) -> 0 | Y76: =ROUND(O76-T76,2) -> 0 | Z76: =SUM(U76:Y76) -> 5969.49
J77: =EDATE($C$13,36) -> 47484 | K77: =U76*(1+N($D$6)/12) -> 0 | L77: =V76*(1+N($D$7)/12) -> 0 | M77: =W76*(1+N($D$8)/12) -> 5994.3629 | N77: =X76*(1+N($D$9)/12) -> 0 | O77: =Y76*(1+N($D$10)/12) -> 0 | P77: =MAX(0,MIN(K77,$C$14-(0)-(MIN(L77,N($E$7))+MIN(M77,N($E$8))+MIN(N77,N($E$9))+MIN(O77,N($E$10))))) -> 0 | Q77: =MAX(0,MIN(L77,$C$14-(P77)-(MIN(M77,N($E$8))+MIN(N77,N($E$9))+MIN(O77,N($E$10))))) -> 0 | R77: =MAX(0,MIN(M77,$C$14-(P77+Q77)-(MIN(N77,N($E$9))+MIN(O77,N($E$10))))) -> 645 | S77: =MAX(0,MIN(N77,$C$14-(P77+Q77+R77)-(MIN(O77,N($E$10))))) -> 0 | T77: =MAX(0,MIN(O77,$C$14-(P77+Q77+R77+S77)-(0))) -> 0 | U77: =ROUND(K77-P77,2) -> 0 | V77: =ROUND(L77-Q77,2) -> 0 | W77: =ROUND(M77-R77,2) -> 5349.36 | X77: =ROUND(N77-S77,2) -> 0 | Y77: =ROUND(O77-T77,2) -> 0 | Z77: =SUM(U77:Y77) -> 5349.36
J78: =EDATE($C$13,37) -> 47515 | K78: =U77*(1+N($D$6)/12) -> 0 | L78: =V77*(1+N($D$7)/12) -> 0 | M78: =W77*(1+N($D$8)/12) -> 5371.649 | N78: =X77*(1+N($D$9)/12) -> 0 | O78: =Y77*(1+N($D$10)/12) -> 0 | P78: =MAX(0,MIN(K78,$C$14-(0)-(MIN(L78,N($E$7))+MIN(M78,N($E$8))+MIN(N78,N($E$9))+MIN(O78,N($E$10))))) -> 0 | Q78: =MAX(0,MIN(L78,$C$14-(P78)-(MIN(M78,N($E$8))+MIN(N78,N($E$9))+MIN(O78,N($E$10))))) -> 0 | R78: =MAX(0,MIN(M78,$C$14-(P78+Q78)-(MIN(N78,N($E$9))+MIN(O78,N($E$10))))) -> 645 | S78: =MAX(0,MIN(N78,$C$14-(P78+Q78+R78)-(MIN(O78,N($E$10))))) -> 0 | T78: =MAX(0,MIN(O78,$C$14-(P78+Q78+R78+S78)-(0))) -> 0 | U78: =ROUND(K78-P78,2) -> 0 | V78: =ROUND(L78-Q78,2) -> 0 | W78: =ROUND(M78-R78,2) -> 4726.65 | X78: =ROUND(N78-S78,2) -> 0 | Y78: =ROUND(O78-T78,2) -> 0 | Z78: =SUM(U78:Y78) -> 4726.65
J79: =EDATE($C$13,38) -> 47543 | K79: =U78*(1+N($D$6)/12) -> 0 | L79: =V78*(1+N($D$7)/12) -> 0 | M79: =W78*(1+N($D$8)/12) -> 4746.3444 | N79: =X78*(1+N($D$9)/12) -> 0 | O79: =Y78*(1+N($D$10)/12) -> 0 | P79: =MAX(0,MIN(K79,$C$14-(0)-(MIN(L79,N($E$7))+MIN(M79,N($E$8))+MIN(N79,N($E$9))+MIN(O79,N($E$10))))) -> 0 | Q79: =MAX(0,MIN(L79,$C$14-(P79)-(MIN(M79,N($E$8))+MIN(N79,N($E$9))+MIN(O79,N($E$10))))) -> 0 | R79: =MAX(0,MIN(M79,$C$14-(P79+Q79)-(MIN(N79,N($E$9))+MIN(O79,N($E$10))))) -> 645 | S79: =MAX(0,MIN(N79,$C$14-(P79+Q79+R79)-(MIN(O79,N($E$10))))) -> 0 | T79: =MAX(0,MIN(O79,$C$14-(P79+Q79+R79+S79)-(0))) -> 0 | U79: =ROUND(K79-P79,2) -> 0 | V79: =ROUND(L79-Q79,2) -> 0 | W79: =ROUND(M79-R79,2) -> 4101.34 | X79: =ROUND(N79-S79,2) -> 0 | Y79: =ROUND(O79-T79,2) -> 0 | Z79: =SUM(U79:Y79) -> 4101.34
J80: =EDATE($C$13,39) -> 47574 | K80: =U79*(1+N($D$6)/12) -> 0 | L80: =V79*(1+N($D$7)/12) -> 0 | M80: =W79*(1+N($D$8)/12) -> 4118.4289 | N80: =X79*(1+N($D$9)/12) -> 0 | O80: =Y79*(1+N($D$10)/12) -> 0 | P80: =MAX(0,MIN(K80,$C$14-(0)-(MIN(L80,N($E$7))+MIN(M80,N($E$8))+MIN(N80,N($E$9))+MIN(O80,N($E$10))))) -> 0 | Q80: =MAX(0,MIN(L80,$C$14-(P80)-(MIN(M80,N($E$8))+MIN(N80,N($E$9))+MIN(O80,N($E$10))))) -> 0 | R80: =MAX(0,MIN(M80,$C$14-(P80+Q80)-(MIN(N80,N($E$9))+MIN(O80,N($E$10))))) -> 645 | S80: =MAX(0,MIN(N80,$C$14-(P80+Q80+R80)-(MIN(O80,N($E$10))))) -> 0 | T80: =MAX(0,MIN(O80,$C$14-(P80+Q80+R80+S80)-(0))) -> 0 | U80: =ROUND(K80-P80,2) -> 0 | V80: =ROUND(L80-Q80,2) -> 0 | W80: =ROUND(M80-R80,2) -> 3473.43 | X80: =ROUND(N80-S80,2) -> 0 | Y80: =ROUND(O80-T80,2) -> 0 | Z80: =SUM(U80:Y80) -> 3473.43
J81: =EDATE($C$13,40) -> 47604 | K81: =U80*(1+N($D$6)/12) -> 0 | L81: =V80*(1+N($D$7)/12) -> 0 | M81: =W80*(1+N($D$8)/12) -> 3487.9026 | N81: =X80*(1+N($D$9)/12) -> 0 | O81: =Y80*(1+N($D$10)/12) -> 0 | P81: =MAX(0,MIN(K81,$C$14-(0)-(MIN(L81,N($E$7))+MIN(M81,N($E$8))+MIN(N81,N($E$9))+MIN(O81,N($E$10))))) -> 0 | Q81: =MAX(0,MIN(L81,$C$14-(P81)-(MIN(M81,N($E$8))+MIN(N81,N($E$9))+MIN(O81,N($E$10))))) -> 0 | R81: =MAX(0,MIN(M81,$C$14-(P81+Q81)-(MIN(N81,N($E$9))+MIN(O81,N($E$10))))) -> 645 | S81: =MAX(0,MIN(N81,$C$14-(P81+Q81+R81)-(MIN(O81,N($E$10))))) -> 0 | T81: =MAX(0,MIN(O81,$C$14-(P81+Q81+R81+S81)-(0))) -> 0 | U81: =ROUND(K81-P81,2) -> 0 | V81: =ROUND(L81-Q81,2) -> 0 | W81: =ROUND(M81-R81,2) -> 2842.9 | X81: =ROUND(N81-S81,2) -> 0 | Y81: =ROUND(O81-T81,2) -> 0 | Z81: =SUM(U81:Y81) -> 2842.9
J82: =EDATE($C$13,41) -> 47635 | K82: =U81*(1+N($D$6)/12) -> 0 | L82: =V81*(1+N($D$7)/12) -> 0 | M82: =W81*(1+N($D$8)/12) -> 2854.7454 | N82: =X81*(1+N($D$9)/12) -> 0 | O82: =Y81*(1+N($D$10)/12) -> 0 | P82: =MAX(0,MIN(K82,$C$14-(0)-(MIN(L82,N($E$7))+MIN(M82,N($E$8))+MIN(N82,N($E$9))+MIN(O82,N($E$10))))) -> 0 | Q82: =MAX(0,MIN(L82,$C$14-(P82)-(MIN(M82,N($E$8))+MIN(N82,N($E$9))+MIN(O82,N($E$10))))) -> 0 | R82: =MAX(0,MIN(M82,$C$14-(P82+Q82)-(MIN(N82,N($E$9))+MIN(O82,N($E$10))))) -> 645 | S82: =MAX(0,MIN(N82,$C$14-(P82+Q82+R82)-(MIN(O82,N($E$10))))) -> 0 | T82: =MAX(0,MIN(O82,$C$14-(P82+Q82+R82+S82)-(0))) -> 0 | U82: =ROUND(K82-P82,2) -> 0 | V82: =ROUND(L82-Q82,2) -> 0 | W82: =ROUND(M82-R82,2) -> 2209.75 | X82: =ROUND(N82-S82,2) -> 0 | Y82: =ROUND(O82-T82,2) -> 0 | Z82: =SUM(U82:Y82) -> 2209.75
J83: =EDATE($C$13,42) -> 47665 | K83: =U82*(1+N($D$6)/12) -> 0 | L83: =V82*(1+N($D$7)/12) -> 0 | M83: =W82*(1+N($D$8)/12) -> 2218.9573 | N83: =X82*(1+N($D$9)/12) -> 0 | O83: =Y82*(1+N($D$10)/12) -> 0 | P83: =MAX(0,MIN(K83,$C$14-(0)-(MIN(L83,N($E$7))+MIN(M83,N($E$8))+MIN(N83,N($E$9))+MIN(O83,N($E$10))))) -> 0 | Q83: =MAX(0,MIN(L83,$C$14-(P83)-(MIN(M83,N($E$8))+MIN(N83,N($E$9))+MIN(O83,N($E$10))))) -> 0 | R83: =MAX(0,MIN(M83,$C$14-(P83+Q83)-(MIN(N83,N($E$9))+MIN(O83,N($E$10))))) -> 645 | S83: =MAX(0,MIN(N83,$C$14-(P83+Q83+R83)-(MIN(O83,N($E$10))))) -> 0 | T83: =MAX(0,MIN(O83,$C$14-(P83+Q83+R83+S83)-(0))) -> 0 | U83: =ROUND(K83-P83,2) -> 0 | V83: =ROUND(L83-Q83,2) -> 0 | W83: =ROUND(M83-R83,2) -> 1573.96 | X83: =ROUND(N83-S83,2) -> 0 | Y83: =ROUND(O83-T83,2) -> 0 | Z83: =SUM(U83:Y83) -> 1573.96
J84: =EDATE($C$13,43) -> 47696 | K84: =U83*(1+N($D$6)/12) -> 0 | L84: =V83*(1+N($D$7)/12) -> 0 | M84: =W83*(1+N($D$8)/12) -> 1580.5182 | N84: =X83*(1+N($D$9)/12) -> 0 | O84: =Y83*(1+N($D$10)/12) -> 0 | P84: =MAX(0,MIN(K84,$C$14-(0)-(MIN(L84,N($E$7))+MIN(M84,N($E$8))+MIN(N84,N($E$9))+MIN(O84,N($E$10))))) -> 0 | Q84: =MAX(0,MIN(L84,$C$14-(P84)-(MIN(M84,N($E$8))+MIN(N84,N($E$9))+MIN(O84,N($E$10))))) -> 0 | R84: =MAX(0,MIN(M84,$C$14-(P84+Q84)-(MIN(N84,N($E$9))+MIN(O84,N($E$10))))) -> 645 | S84: =MAX(0,MIN(N84,$C$14-(P84+Q84+R84)-(MIN(O84,N($E$10))))) -> 0 | T84: =MAX(0,MIN(O84,$C$14-(P84+Q84+R84+S84)-(0))) -> 0 | U84: =ROUND(K84-P84,2) -> 0 | V84: =ROUND(L84-Q84,2) -> 0 | W84: =ROUND(M84-R84,2) -> 935.52 | X84: =ROUND(N84-S84,2) -> 0 | Y84: =ROUND(O84-T84,2) -> 0 | Z84: =SUM(U84:Y84) -> 935.52
J85: =EDATE($C$13,44) -> 47727 | K85: =U84*(1+N($D$6)/12) -> 0 | L85: =V84*(1+N($D$7)/12) -> 0 | M85: =W84*(1+N($D$8)/12) -> 939.418 | N85: =X84*(1+N($D$9)/12) -> 0 | O85: =Y84*(1+N($D$10)/12) -> 0 | P85: =MAX(0,MIN(K85,$C$14-(0)-(MIN(L85,N($E$7))+MIN(M85,N($E$8))+MIN(N85,N($E$9))+MIN(O85,N($E$10))))) -> 0 | Q85: =MAX(0,MIN(L85,$C$14-(P85)-(MIN(M85,N($E$8))+MIN(N85,N($E$9))+MIN(O85,N($E$10))))) -> 0 | R85: =MAX(0,MIN(M85,$C$14-(P85+Q85)-(MIN(N85,N($E$9))+MIN(O85,N($E$10))))) -> 645 | S85: =MAX(0,MIN(N85,$C$14-(P85+Q85+R85)-(MIN(O85,N($E$10))))) -> 0 | T85: =MAX(0,MIN(O85,$C$14-(P85+Q85+R85+S85)-(0))) -> 0 | U85: =ROUND(K85-P85,2) -> 0 | V85: =ROUND(L85-Q85,2) -> 0 | W85: =ROUND(M85-R85,2) -> 294.42 | X85: =ROUND(N85-S85,2) -> 0 | Y85: =ROUND(O85-T85,2) -> 0 | Z85: =SUM(U85:Y85) -> 294.42
J86: =EDATE($C$13,45) -> 47757 | K86: =U85*(1+N($D$6)/12) -> 0 | L86: =V85*(1+N($D$7)/12) -> 0 | M86: =W85*(1+N($D$8)/12) -> 295.64675 | N86: =X85*(1+N($D$9)/12) -> 0 | O86: =Y85*(1+N($D$10)/12) -> 0 | P86: =MAX(0,MIN(K86,$C$14-(0)-(MIN(L86,N($E$7))+MIN(M86,N($E$8))+MIN(N86,N($E$9))+MIN(O86,N($E$10))))) -> 0 | Q86: =MAX(0,MIN(L86,$C$14-(P86)-(MIN(M86,N($E$8))+MIN(N86,N($E$9))+MIN(O86,N($E$10))))) -> 0 | R86: =MAX(0,MIN(M86,$C$14-(P86+Q86)-(MIN(N86,N($E$9))+MIN(O86,N($E$10))))) -> 295.64675 | S86: =MAX(0,MIN(N86,$C$14-(P86+Q86+R86)-(MIN(O86,N($E$10))))) -> 0 | T86: =MAX(0,MIN(O86,$C$14-(P86+Q86+R86+S86)-(0))) -> 0 | U86: =ROUND(K86-P86,2) -> 0 | V86: =ROUND(L86-Q86,2) -> 0 | W86: =ROUND(M86-R86,2) -> 0 | X86: =ROUND(N86-S86,2) -> 0 | Y86: =ROUND(O86-T86,2) -> 0 | Z86: =SUM(U86:Y86) -> 0
J87: =EDATE($C$13,46) -> 47788 | K87: =U86*(1+N($D$6)/12) -> 0 | L87: =V86*(1+N($D$7)/12) -> 0 | M87: =W86*(1+N($D$8)/12) -> 0 | N87: =X86*(1+N($D$9)/12) -> 0 | O87: =Y86*(1+N($D$10)/12) -> 0 | P87: =MAX(0,MIN(K87,$C$14-(0)-(MIN(L87,N($E$7))+MIN(M87,N($E$8))+MIN(N87,N($E$9))+MIN(O87,N($E$10))))) -> 0 | Q87: =MAX(0,MIN(L87,$C$14-(P87)-(MIN(M87,N($E$8))+MIN(N87,N($E$9))+MIN(O87,N($E$10))))) -> 0 | R87: =MAX(0,MIN(M87,$C$14-(P87+Q87)-(MIN(N87,N($E$9))+MIN(O87,N($E$10))))) -> 0 | S87: =MAX(0,MIN(N87,$C$14-(P87+Q87+R87)-(MIN(O87,N($E$10))))) -> 0 | T87: =MAX(0,MIN(O87,$C$14-(P87+Q87+R87+S87)-(0))) -> 0 | U87: =ROUND(K87-P87,2) -> 0 | V87: =ROUND(L87-Q87,2) -> 0 | W87: =ROUND(M87-R87,2) -> 0 | X87: =ROUND(N87-S87,2) -> 0 | Y87: =ROUND(O87-T87,2) -> 0 | Z87: =SUM(U87:Y87) -> 0
J88: =EDATE($C$13,47) -> 47818 | K88: =U87*(1+N($D$6)/12) -> 0 | L88: =V87*(1+N($D$7)/12) -> 0 | M88: =W87*(1+N($D$8)/12) -> 0 | N88: =X87*(1+N($D$9)/12) -> 0 | O88: =Y87*(1+N($D$10)/12) -> 0 | P88: =MAX(0,MIN(K88,$C$14-(0)-(MIN(L88,N($E$7))+MIN(M88,N($E$8))+MIN(N88,N($E$9))+MIN(O88,N($E$10))))) -> 0 | Q88: =MAX(0,MIN(L88,$C$14-(P88)-(MIN(M88,N($E$8))+MIN(N88,N($E$9))+MIN(O88,N($E$10))))) -> 0 | R88: =MAX(0,MIN(M88,$C$14-(P88+Q88)-(MIN(N88,N($E$9))+MIN(O88,N($E$10))))) -> 0 | S88: =MAX(0,MIN(N88,$C$14-(P88+Q88+R88)-(MIN(O88,N($E$10))))) -> 0 | T88: =MAX(0,MIN(O88,$C$14-(P88+Q88+R88+S88)-(0))) -> 0 | U88: =ROUND(K88-P88,2) -> 0 | V88: =ROUND(L88-Q88,2) -> 0 | W88: =ROUND(M88-R88,2) -> 0 | X88: =ROUND(N88-S88,2) -> 0 | Y88: =ROUND(O88-T88,2) -> 0 | Z88: =SUM(U88:Y88) -> 0
J89: =EDATE($C$13,48) -> 47849 | K89: =U88*(1+N($D$6)/12) -> 0 | L89: =V88*(1+N($D$7)/12) -> 0 | M89: =W88*(1+N($D$8)/12) -> 0 | N89: =X88*(1+N($D$9)/12) -> 0 | O89: =Y88*(1+N($D$10)/12) -> 0 | P89: =MAX(0,MIN(K89,$C$14-(0)-(MIN(L89,N($E$7))+MIN(M89,N($E$8))+MIN(N89,N($E$9))+MIN(O89,N($E$10))))) -> 0 | Q89: =MAX(0,MIN(L89,$C$14-(P89)-(MIN(M89,N($E$8))+MIN(N89,N($E$9))+MIN(O89,N($E$10))))) -> 0 | R89: =MAX(0,MIN(M89,$C$14-(P89+Q89)-(MIN(N89,N($E$9))+MIN(O89,N($E$10))))) -> 0 | S89: =MAX(0,MIN(N89,$C$14-(P89+Q89+R89)-(MIN(O89,N($E$10))))) -> 0 | T89: =MAX(0,MIN(O89,$C$14-(P89+Q89+R89+S89)-(0))) -> 0 | U89: =ROUND(K89-P89,2) -> 0 | V89: =ROUND(L89-Q89,2) -> 0 | W89: =ROUND(M89-R89,2) -> 0 | X89: =ROUND(N89-S89,2) -> 0 | Y89: =ROUND(O89-T89,2) -> 0 | Z89: =SUM(U89:Y89) -> 0
J90: =EDATE($C$13,49) -> 47880 | K90: =U89*(1+N($D$6)/12) -> 0 | L90: =V89*(1+N($D$7)/12) -> 0 | M90: =W89*(1+N($D$8)/12) -> 0 | N90: =X89*(1+N($D$9)/12) -> 0 | O90: =Y89*(1+N($D$10)/12) -> 0 | P90: =MAX(0,MIN(K90,$C$14-(0)-(MIN(L90,N($E$7))+MIN(M90,N($E$8))+MIN(N90,N($E$9))+MIN(O90,N($E$10))))) -> 0 | Q90: =MAX(0,MIN(L90,$C$14-(P90)-(MIN(M90,N($E$8))+MIN(N90,N($E$9))+MIN(O90,N($E$10))))) -> 0 | R90: =MAX(0,MIN(M90,$C$14-(P90+Q90)-(MIN(N90,N($E$9))+MIN(O90,N($E$10))))) -> 0 | S90: =MAX(0,MIN(N90,$C$14-(P90+Q90+R90)-(MIN(O90,N($E$10))))) -> 0 | T90: =MAX(0,MIN(O90,$C$14-(P90+Q90+R90+S90)-(0))) -> 0 | U90: =ROUND(K90-P90,2) -> 0 | V90: =ROUND(L90-Q90,2) -> 0 | W90: =ROUND(M90-R90,2) -> 0 | X90: =ROUND(N90-S90,2) -> 0 | Y90: =ROUND(O90-T90,2) -> 0 | Z90: =SUM(U90:Y90) -> 0
J91: =EDATE($C$13,50) -> 47908 | K91: =U90*(1+N($D$6)/12) -> 0 | L91: =V90*(1+N($D$7)/12) -> 0 | M91: =W90*(1+N($D$8)/12) -> 0 | N91: =X90*(1+N($D$9)/12) -> 0 | O91: =Y90*(1+N($D$10)/12) -> 0 | P91: =MAX(0,MIN(K91,$C$14-(0)-(MIN(L91,N($E$7))+MIN(M91,N($E$8))+MIN(N91,N($E$9))+MIN(O91,N($E$10))))) -> 0 | Q91: =MAX(0,MIN(L91,$C$14-(P91)-(MIN(M91,N($E$8))+MIN(N91,N($E$9))+MIN(O91,N($E$10))))) -> 0 | R91: =MAX(0,MIN(M91,$C$14-(P91+Q91)-(MIN(N91,N($E$9))+MIN(O91,N($E$10))))) -> 0 | S91: =MAX(0,MIN(N91,$C$14-(P91+Q91+R91)-(MIN(O91,N($E$10))))) -> 0 | T91: =MAX(0,MIN(O91,$C$14-(P91+Q91+R91+S91)-(0))) -> 0 | U91: =ROUND(K91-P91,2) -> 0 | V91: =ROUND(L91-Q91,2) -> 0 | W91: =ROUND(M91-R91,2) -> 0 | X91: =ROUND(N91-S91,2) -> 0 | Y91: =ROUND(O91-T91,2) -> 0 | Z91: =SUM(U91:Y91) -> 0
J92: =EDATE($C$13,51) -> 47939 | K92: =U91*(1+N($D$6)/12) -> 0 | L92: =V91*(1+N($D$7)/12) -> 0 | M92: =W91*(1+N($D$8)/12) -> 0 | N92: =X91*(1+N($D$9)/12) -> 0 | O92: =Y91*(1+N($D$10)/12) -> 0 | P92: =MAX(0,MIN(K92,$C$14-(0)-(MIN(L92,N($E$7))+MIN(M92,N($E$8))+MIN(N92,N($E$9))+MIN(O92,N($E$10))))) -> 0 | Q92: =MAX(0,MIN(L92,$C$14-(P92)-(MIN(M92,N($E$8))+MIN(N92,N($E$9))+MIN(O92,N($E$10))))) -> 0 | R92: =MAX(0,MIN(M92,$C$14-(P92+Q92)-(MIN(N92,N($E$9))+MIN(O92,N($E$10))))) -> 0 | S92: =MAX(0,MIN(N92,$C$14-(P92+Q92+R92)-(MIN(O92,N($E$10))))) -> 0 | T92: =MAX(0,MIN(O92,$C$14-(P92+Q92+R92+S92)-(0))) -> 0 | U92: =ROUND(K92-P92,2) -> 0 | V92: =ROUND(L92-Q92,2) -> 0 | W92: =ROUND(M92-R92,2) -> 0 | X92: =ROUND(N92-S92,2) -> 0 | Y92: =ROUND(O92-T92,2) -> 0 | Z92: =SUM(U92:Y92) -> 0
J93: =EDATE($C$13,52) -> 47969 | K93: =U92*(1+N($D$6)/12) -> 0 | L93: =V92*(1+N($D$7)/12) -> 0 | M93: =W92*(1+N($D$8)/12) -> 0 | N93: =X92*(1+N($D$9)/12) -> 0 | O93: =Y92*(1+N($D$10)/12) -> 0 | P93: =MAX(0,MIN(K93,$C$14-(0)-(MIN(L93,N($E$7))+MIN(M93,N($E$8))+MIN(N93,N($E$9))+MIN(O93,N($E$10))))) -> 0 | Q93: =MAX(0,MIN(L93,$C$14-(P93)-(MIN(M93,N($E$8))+MIN(N93,N($E$9))+MIN(O93,N($E$10))))) -> 0 | R93: =MAX(0,MIN(M93,$C$14-(P93+Q93)-(MIN(N93,N($E$9))+MIN(O93,N($E$10))))) -> 0 | S93: =MAX(0,MIN(N93,$C$14-(P93+Q93+R93)-(MIN(O93,N($E$10))))) -> 0 | T93: =MAX(0,MIN(O93,$C$14-(P93+Q93+R93+S93)-(0))) -> 0 | U93: =ROUND(K93-P93,2) -> 0 | V93: =ROUND(L93-Q93,2) -> 0 | W93: =ROUND(M93-R93,2) -> 0 | X93: =ROUND(N93-S93,2) -> 0 | Y93: =ROUND(O93-T93,2) -> 0 | Z93: =SUM(U93:Y93) -> 0
J94: =EDATE($C$13,53) -> 48000 | K94: =U93*(1+N($D$6)/12) -> 0 | L94: =V93*(1+N($D$7)/12) -> 0 | M94: =W93*(1+N($D$8)/12) -> 0 | N94: =X93*(1+N($D$9)/12) -> 0 | O94: =Y93*(1+N($D$10)/12) -> 0 | P94: =MAX(0,MIN(K94,$C$14-(0)-(MIN(L94,N($E$7))+MIN(M94,N($E$8))+MIN(N94,N($E$9))+MIN(O94,N($E$10))))) -> 0 | Q94: =MAX(0,MIN(L94,$C$14-(P94)-(MIN(M94,N($E$8))+MIN(N94,N($E$9))+MIN(O94,N($E$10))))) -> 0 | R94: =MAX(0,MIN(M94,$C$14-(P94+Q94)-(MIN(N94,N($E$9))+MIN(O94,N($E$10))))) -> 0 | S94: =MAX(0,MIN(N94,$C$14-(P94+Q94+R94)-(MIN(O94,N($E$10))))) -> 0 | T94: =MAX(0,MIN(O94,$C$14-(P94+Q94+R94+S94)-(0))) -> 0 | U94: =ROUND(K94-P94,2) -> 0 | V94: =ROUND(L94-Q94,2) -> 0 | W94: =ROUND(M94-R94,2) -> 0 | X94: =ROUND(N94-S94,2) -> 0 | Y94: =ROUND(O94-T94,2) -> 0 | Z94: =SUM(U94:Y94) -> 0
J95: =EDATE($C$13,54) -> 48030 | K95: =U94*(1+N($D$6)/12) -> 0 | L95: =V94*(1+N($D$7)/12) -> 0 | M95: =W94*(1+N($D$8)/12) -> 0 | N95: =X94*(1+N($D$9)/12) -> 0 | O95: =Y94*(1+N($D$10)/12) -> 0 | P95: =MAX(0,MIN(K95,$C$14-(0)-(MIN(L95,N($E$7))+MIN(M95,N($E$8))+MIN(N95,N($E$9))+MIN(O95,N($E$10))))) -> 0 | Q95: =MAX(0,MIN(L95,$C$14-(P95)-(MIN(M95,N($E$8))+MIN(N95,N($E$9))+MIN(O95,N($E$10))))) -> 0 | R95: =MAX(0,MIN(M95,$C$14-(P95+Q95)-(MIN(N95,N($E$9))+MIN(O95,N($E$10))))) -> 0 | S95: =MAX(0,MIN(N95,$C$14-(P95+Q95+R95)-(MIN(O95,N($E$10))))) -> 0 | T95: =MAX(0,MIN(O95,$C$14-(P95+Q95+R95+S95)-(0))) -> 0 | U95: =ROUND(K95-P95,2) -> 0 | V95: =ROUND(L95-Q95,2) -> 0 | W95: =ROUND(M95-R95,2) -> 0 | X95: =ROUND(N95-S95,2) -> 0 | Y95: =ROUND(O95-T95,2) -> 0 | Z95: =SUM(U95:Y95) -> 0
J96: =EDATE($C$13,55) -> 48061 | K96: =U95*(1+N($D$6)/12) -> 0 | L96: =V95*(1+N($D$7)/12) -> 0 | M96: =W95*(1+N($D$8)/12) -> 0 | N96: =X95*(1+N($D$9)/12) -> 0 | O96: =Y95*(1+N($D$10)/12) -> 0 | P96: =MAX(0,MIN(K96,$C$14-(0)-(MIN(L96,N($E$7))+MIN(M96,N($E$8))+MIN(N96,N($E$9))+MIN(O96,N($E$10))))) -> 0 | Q96: =MAX(0,MIN(L96,$C$14-(P96)-(MIN(M96,N($E$8))+MIN(N96,N($E$9))+MIN(O96,N($E$10))))) -> 0 | R96: =MAX(0,MIN(M96,$C$14-(P96+Q96)-(MIN(N96,N($E$9))+MIN(O96,N($E$10))))) -> 0 | S96: =MAX(0,MIN(N96,$C$14-(P96+Q96+R96)-(MIN(O96,N($E$10))))) -> 0 | T96: =MAX(0,MIN(O96,$C$14-(P96+Q96+R96+S96)-(0))) -> 0 | U96: =ROUND(K96-P96,2) -> 0 | V96: =ROUND(L96-Q96,2) -> 0 | W96: =ROUND(M96-R96,2) -> 0 | X96: =ROUND(N96-S96,2) -> 0 | Y96: =ROUND(O96-T96,2) -> 0 | Z96: =SUM(U96:Y96) -> 0
J97: =EDATE($C$13,56) -> 48092 | K97: =U96*(1+N($D$6)/12) -> 0 | L97: =V96*(1+N($D$7)/12) -> 0 | M97: =W96*(1+N($D$8)/12) -> 0 | N97: =X96*(1+N($D$9)/12) -> 0 | O97: =Y96*(1+N($D$10)/12) -> 0 | P97: =MAX(0,MIN(K97,$C$14-(0)-(MIN(L97,N($E$7))+MIN(M97,N($E$8))+MIN(N97,N($E$9))+MIN(O97,N($E$10))))) -> 0 | Q97: =MAX(0,MIN(L97,$C$14-(P97)-(MIN(M97,N($E$8))+MIN(N97,N($E$9))+MIN(O97,N($E$10))))) -> 0 | R97: =MAX(0,MIN(M97,$C$14-(P97+Q97)-(MIN(N97,N($E$9))+MIN(O97,N($E$10))))) -> 0 | S97: =MAX(0,MIN(N97,$C$14-(P97+Q97+R97)-(MIN(O97,N($E$10))))) -> 0 | T97: =MAX(0,MIN(O97,$C$14-(P97+Q97+R97+S97)-(0))) -> 0 | U97: =ROUND(K97-P97,2) -> 0 | V97: =ROUND(L97-Q97,2) -> 0 | W97: =ROUND(M97-R97,2) -> 0 | X97: =ROUND(N97-S97,2) -> 0 | Y97: =ROUND(O97-T97,2) -> 0 | Z97: =SUM(U97:Y97) -> 0
J98: =EDATE($C$13,57) -> 48122 | K98: =U97*(1+N($D$6)/12) -> 0 | L98: =V97*(1+N($D$7)/12) -> 0 | M98: =W97*(1+N($D$8)/12) -> 0 | N98: =X97*(1+N($D$9)/12) -> 0 | O98: =Y97*(1+N($D$10)/12) -> 0 | P98: =MAX(0,MIN(K98,$C$14-(0)-(MIN(L98,N($E$7))+MIN(M98,N($E$8))+MIN(N98,N($E$9))+MIN(O98,N($E$10))))) -> 0 | Q98: =MAX(0,MIN(L98,$C$14-(P98)-(MIN(M98,N($E$8))+MIN(N98,N($E$9))+MIN(O98,N($E$10))))) -> 0 | R98: =MAX(0,MIN(M98,$C$14-(P98+Q98)-(MIN(N98,N($E$9))+MIN(O98,N($E$10))))) -> 0 | S98: =MAX(0,MIN(N98,$C$14-(P98+Q98+R98)-(MIN(O98,N($E$10))))) -> 0 | T98: =MAX(0,MIN(O98,$C$14-(P98+Q98+R98+S98)-(0))) -> 0 | U98: =ROUND(K98-P98,2) -> 0 | V98: =ROUND(L98-Q98,2) -> 0 | W98: =ROUND(M98-R98,2) -> 0 | X98: =ROUND(N98-S98,2) -> 0 | Y98: =ROUND(O98-T98,2) -> 0 | Z98: =SUM(U98:Y98) -> 0
J99: =EDATE($C$13,58) -> 48153 | K99: =U98*(1+N($D$6)/12) -> 0 | L99: =V98*(1+N($D$7)/12) -> 0 | M99: =W98*(1+N($D$8)/12) -> 0 | N99: =X98*(1+N($D$9)/12) -> 0 | O99: =Y98*(1+N($D$10)/12) -> 0 | P99: =MAX(0,MIN(K99,$C$14-(0)-(MIN(L99,N($E$7))+MIN(M99,N($E$8))+MIN(N99,N($E$9))+MIN(O99,N($E$10))))) -> 0 | Q99: =MAX(0,MIN(L99,$C$14-(P99)-(MIN(M99,N($E$8))+MIN(N99,N($E$9))+MIN(O99,N($E$10))))) -> 0 | R99: =MAX(0,MIN(M99,$C$14-(P99+Q99)-(MIN(N99,N($E$9))+MIN(O99,N($E$10))))) -> 0 | S99: =MAX(0,MIN(N99,$C$14-(P99+Q99+R99)-(MIN(O99,N($E$10))))) -> 0 | T99: =MAX(0,MIN(O99,$C$14-(P99+Q99+R99+S99)-(0))) -> 0 | U99: =ROUND(K99-P99,2) -> 0 | V99: =ROUND(L99-Q99,2) -> 0 | W99: =ROUND(M99-R99,2) -> 0 | X99: =ROUND(N99-S99,2) -> 0 | Y99: =ROUND(O99-T99,2) -> 0 | Z99: =SUM(U99:Y99) -> 0
J100: =EDATE($C$13,59) -> 48183 | K100: =U99*(1+N($D$6)/12) -> 0 | L100: =V99*(1+N($D$7)/12) -> 0 | M100: =W99*(1+N($D$8)/12) -> 0 | N100: =X99*(1+N($D$9)/12) -> 0 | O100: =Y99*(1+N($D$10)/12) -> 0 | P100: =MAX(0,MIN(K100,$C$14-(0)-(MIN(L100,N($E$7))+MIN(M100,N($E$8))+MIN(N100,N($E$9))+MIN(O100,N($E$10))))) -> 0 | Q100: =MAX(0,MIN(L100,$C$14-(P100)-(MIN(M100,N($E$8))+MIN(N100,N($E$9))+MIN(O100,N($E$10))))) -> 0 | R100: =MAX(0,MIN(M100,$C$14-(P100+Q100)-(MIN(N100,N($E$9))+MIN(O100,N($E$10))))) -> 0 | S100: =MAX(0,MIN(N100,$C$14-(P100+Q100+R100)-(MIN(O100,N($E$10))))) -> 0 | T100: =MAX(0,MIN(O100,$C$14-(P100+Q100+R100+S100)-(0))) -> 0 | U100: =ROUND(K100-P100,2) -> 0 | V100: =ROUND(L100-Q100,2) -> 0 | W100: =ROUND(M100-R100,2) -> 0 | X100: =ROUND(N100-S100,2) -> 0 | Y100: =ROUND(O100-T100,2) -> 0 | Z100: =SUM(U100:Y100) -> 0
J101: =EDATE($C$13,60) -> 48214 | K101: =U100*(1+N($D$6)/12) -> 0 | L101: =V100*(1+N($D$7)/12) -> 0 | M101: =W100*(1+N($D$8)/12) -> 0 | N101: =X100*(1+N($D$9)/12) -> 0 | O101: =Y100*(1+N($D$10)/12) -> 0 | P101: =MAX(0,MIN(K101,$C$14-(0)-(MIN(L101,N($E$7))+MIN(M101,N($E$8))+MIN(N101,N($E$9))+MIN(O101,N($E$10))))) -> 0 | Q101: =MAX(0,MIN(L101,$C$14-(P101)-(MIN(M101,N($E$8))+MIN(N101,N($E$9))+MIN(O101,N($E$10))))) -> 0 | R101: =MAX(0,MIN(M101,$C$14-(P101+Q101)-(MIN(N101,N($E$9))+MIN(O101,N($E$10))))) -> 0 | S101: =MAX(0,MIN(N101,$C$14-(P101+Q101+R101)-(MIN(O101,N($E$10))))) -> 0 | T101: =MAX(0,MIN(O101,$C$14-(P101+Q101+R101+S101)-(0))) -> 0 | U101: =ROUND(K101-P101,2) -> 0 | V101: =ROUND(L101-Q101,2) -> 0 | W101: =ROUND(M101-R101,2) -> 0 | X101: =ROUND(N101-S101,2) -> 0 | Y101: =ROUND(O101-T101,2) -> 0 | Z101: =SUM(U101:Y101) -> 0
J102: =EDATE($C$13,61) -> 48245 | K102: =U101*(1+N($D$6)/12) -> 0 | L102: =V101*(1+N($D$7)/12) -> 0 | M102: =W101*(1+N($D$8)/12) -> 0 | N102: =X101*(1+N($D$9)/12) -> 0 | O102: =Y101*(1+N($D$10)/12) -> 0 | P102: =MAX(0,MIN(K102,$C$14-(0)-(MIN(L102,N($E$7))+MIN(M102,N($E$8))+MIN(N102,N($E$9))+MIN(O102,N($E$10))))) -> 0 | Q102: =MAX(0,MIN(L102,$C$14-(P102)-(MIN(M102,N($E$8))+MIN(N102,N($E$9))+MIN(O102,N($E$10))))) -> 0 | R102: =MAX(0,MIN(M102,$C$14-(P102+Q102)-(MIN(N102,N($E$9))+MIN(O102,N($E$10))))) -> 0 | S102: =MAX(0,MIN(N102,$C$14-(P102+Q102+R102)-(MIN(O102,N($E$10))))) -> 0 | T102: =MAX(0,MIN(O102,$C$14-(P102+Q102+R102+S102)-(0))) -> 0 | U102: =ROUND(K102-P102,2) -> 0 | V102: =ROUND(L102-Q102,2) -> 0 | W102: =ROUND(M102-R102,2) -> 0 | X102: =ROUND(N102-S102,2) -> 0 | Y102: =ROUND(O102-T102,2) -> 0 | Z102: =SUM(U102:Y102) -> 0
J103: =EDATE($C$13,62) -> 48274 | K103: =U102*(1+N($D$6)/12) -> 0 | L103: =V102*(1+N($D$7)/12) -> 0 | M103: =W102*(1+N($D$8)/12) -> 0 | N103: =X102*(1+N($D$9)/12) -> 0 | O103: =Y102*(1+N($D$10)/12) -> 0 | P103: =MAX(0,MIN(K103,$C$14-(0)-(MIN(L103,N($E$7))+MIN(M103,N($E$8))+MIN(N103,N($E$9))+MIN(O103,N($E$10))))) -> 0 | Q103: =MAX(0,MIN(L103,$C$14-(P103)-(MIN(M103,N($E$8))+MIN(N103,N($E$9))+MIN(O103,N($E$10))))) -> 0 | R103: =MAX(0,MIN(M103,$C$14-(P103+Q103)-(MIN(N103,N($E$9))+MIN(O103,N($E$10))))) -> 0 | S103: =MAX(0,MIN(N103,$C$14-(P103+Q103+R103)-(MIN(O103,N($E$10))))) -> 0 | T103: =MAX(0,MIN(O103,$C$14-(P103+Q103+R103+S103)-(0))) -> 0 | U103: =ROUND(K103-P103,2) -> 0 | V103: =ROUND(L103-Q103,2) -> 0 | W103: =ROUND(M103-R103,2) -> 0 | X103: =ROUND(N103-S103,2) -> 0 | Y103: =ROUND(O103-T103,2) -> 0 | Z103: =SUM(U103:Y103) -> 0
J104: =EDATE($C$13,63) -> 48305 | K104: =U103*(1+N($D$6)/12) -> 0 | L104: =V103*(1+N($D$7)/12) -> 0 | M104: =W103*(1+N($D$8)/12) -> 0 | N104: =X103*(1+N($D$9)/12) -> 0 | O104: =Y103*(1+N($D$10)/12) -> 0 | P104: =MAX(0,MIN(K104,$C$14-(0)-(MIN(L104,N($E$7))+MIN(M104,N($E$8))+MIN(N104,N($E$9))+MIN(O104,N($E$10))))) -> 0 | Q104: =MAX(0,MIN(L104,$C$14-(P104)-(MIN(M104,N($E$8))+MIN(N104,N($E$9))+MIN(O104,N($E$10))))) -> 0 | R104: =MAX(0,MIN(M104,$C$14-(P104+Q104)-(MIN(N104,N($E$9))+MIN(O104,N($E$10))))) -> 0 | S104: =MAX(0,MIN(N104,$C$14-(P104+Q104+R104)-(MIN(O104,N($E$10))))) -> 0 | T104: =MAX(0,MIN(O104,$C$14-(P104+Q104+R104+S104)-(0))) -> 0 | U104: =ROUND(K104-P104,2) -> 0 | V104: =ROUND(L104-Q104,2) -> 0 | W104: =ROUND(M104-R104,2) -> 0 | X104: =ROUND(N104-S104,2) -> 0 | Y104: =ROUND(O104-T104,2) -> 0 | Z104: =SUM(U104:Y104) -> 0
J105: =EDATE($C$13,64) -> 48335 | K105: =U104*(1+N($D$6)/12) -> 0 | L105: =V104*(1+N($D$7)/12) -> 0 | M105: =W104*(1+N($D$8)/12) -> 0 | N105: =X104*(1+N($D$9)/12) -> 0 | O105: =Y104*(1+N($D$10)/12) -> 0 | P105: =MAX(0,MIN(K105,$C$14-(0)-(MIN(L105,N($E$7))+MIN(M105,N($E$8))+MIN(N105,N($E$9))+MIN(O105,N($E$10))))) -> 0 | Q105: =MAX(0,MIN(L105,$C$14-(P105)-(MIN(M105,N($E$8))+MIN(N105,N($E$9))+MIN(O105,N($E$10))))) -> 0 | R105: =MAX(0,MIN(M105,$C$14-(P105+Q105)-(MIN(N105,N($E$9))+MIN(O105,N($E$10))))) -> 0 | S105: =MAX(0,MIN(N105,$C$14-(P105+Q105+R105)-(MIN(O105,N($E$10))))) -> 0 | T105: =MAX(0,MIN(O105,$C$14-(P105+Q105+R105+S105)-(0))) -> 0 | U105: =ROUND(K105-P105,2) -> 0 | V105: =ROUND(L105-Q105,2) -> 0 | W105: =ROUND(M105-R105,2) -> 0 | X105: =ROUND(N105-S105,2) -> 0 | Y105: =ROUND(O105-T105,2) -> 0 | Z105: =SUM(U105:Y105) -> 0
J106: =EDATE($C$13,65) -> 48366 | K106: =U105*(1+N($D$6)/12) -> 0 | L106: =V105*(1+N($D$7)/12) -> 0 | M106: =W105*(1+N($D$8)/12) -> 0 | N106: =X105*(1+N($D$9)/12) -> 0 | O106: =Y105*(1+N($D$10)/12) -> 0 | P106: =MAX(0,MIN(K106,$C$14-(0)-(MIN(L106,N($E$7))+MIN(M106,N($E$8))+MIN(N106,N($E$9))+MIN(O106,N($E$10))))) -> 0 | Q106: =MAX(0,MIN(L106,$C$14-(P106)-(MIN(M106,N($E$8))+MIN(N106,N($E$9))+MIN(O106,N($E$10))))) -> 0 | R106: =MAX(0,MIN(M106,$C$14-(P106+Q106)-(MIN(N106,N($E$9))+MIN(O106,N($E$10))))) -> 0 | S106: =MAX(0,MIN(N106,$C$14-(P106+Q106+R106)-(MIN(O106,N($E$10))))) -> 0 | T106: =MAX(0,MIN(O106,$C$14-(P106+Q106+R106+S106)-(0))) -> 0 | U106: =ROUND(K106-P106,2) -> 0 | V106: =ROUND(L106-Q106,2) -> 0 | W106: =ROUND(M106-R106,2) -> 0 | X106: =ROUND(N106-S106,2) -> 0 | Y106: =ROUND(O106-T106,2) -> 0 | Z106: =SUM(U106:Y106) -> 0
J107: =EDATE($C$13,66) -> 48396 | K107: =U106*(1+N($D$6)/12) -> 0 | L107: =V106*(1+N($D$7)/12) -> 0 | M107: =W106*(1+N($D$8)/12) -> 0 | N107: =X106*(1+N($D$9)/12) -> 0 | O107: =Y106*(1+N($D$10)/12) -> 0 | P107: =MAX(0,MIN(K107,$C$14-(0)-(MIN(L107,N($E$7))+MIN(M107,N($E$8))+MIN(N107,N($E$9))+MIN(O107,N($E$10))))) -> 0 | Q107: =MAX(0,MIN(L107,$C$14-(P107)-(MIN(M107,N($E$8))+MIN(N107,N($E$9))+MIN(O107,N($E$10))))) -> 0 | R107: =MAX(0,MIN(M107,$C$14-(P107+Q107)-(MIN(N107,N($E$9))+MIN(O107,N($E$10))))) -> 0 | S107: =MAX(0,MIN(N107,$C$14-(P107+Q107+R107)-(MIN(O107,N($E$10))))) -> 0 | T107: =MAX(0,MIN(O107,$C$14-(P107+Q107+R107+S107)-(0))) -> 0 | U107: =ROUND(K107-P107,2) -> 0 | V107: =ROUND(L107-Q107,2) -> 0 | W107: =ROUND(M107-R107,2) -> 0 | X107: =ROUND(N107-S107,2) -> 0 | Y107: =ROUND(O107-T107,2) -> 0 | Z107: =SUM(U107:Y107) -> 0
J108: =EDATE($C$13,67) -> 48427 | K108: =U107*(1+N($D$6)/12) -> 0 | L108: =V107*(1+N($D$7)/12) -> 0 | M108: =W107*(1+N($D$8)/12) -> 0 | N108: =X107*(1+N($D$9)/12) -> 0 | O108: =Y107*(1+N($D$10)/12) -> 0 | P108: =MAX(0,MIN(K108,$C$14-(0)-(MIN(L108,N($E$7))+MIN(M108,N($E$8))+MIN(N108,N($E$9))+MIN(O108,N($E$10))))) -> 0 | Q108: =MAX(0,MIN(L108,$C$14-(P108)-(MIN(M108,N($E$8))+MIN(N108,N($E$9))+MIN(O108,N($E$10))))) -> 0 | R108: =MAX(0,MIN(M108,$C$14-(P108+Q108)-(MIN(N108,N($E$9))+MIN(O108,N($E$10))))) -> 0 | S108: =MAX(0,MIN(N108,$C$14-(P108+Q108+R108)-(MIN(O108,N($E$10))))) -> 0 | T108: =MAX(0,MIN(O108,$C$14-(P108+Q108+R108+S108)-(0))) -> 0 | U108: =ROUND(K108-P108,2) -> 0 | V108: =ROUND(L108-Q108,2) -> 0 | W108: =ROUND(M108-R108,2) -> 0 | X108: =ROUND(N108-S108,2) -> 0 | Y108: =ROUND(O108-T108,2) -> 0 | Z108: =SUM(U108:Y108) -> 0
J109: =EDATE($C$13,68) -> 48458 | K109: =U108*(1+N($D$6)/12) -> 0 | L109: =V108*(1+N($D$7)/12) -> 0 | M109: =W108*(1+N($D$8)/12) -> 0 | N109: =X108*(1+N($D$9)/12) -> 0 | O109: =Y108*(1+N($D$10)/12) -> 0 | P109: =MAX(0,MIN(K109,$C$14-(0)-(MIN(L109,N($E$7))+MIN(M109,N($E$8))+MIN(N109,N($E$9))+MIN(O109,N($E$10))))) -> 0 | Q109: =MAX(0,MIN(L109,$C$14-(P109)-(MIN(M109,N($E$8))+MIN(N109,N($E$9))+MIN(O109,N($E$10))))) -> 0 | R109: =MAX(0,MIN(M109,$C$14-(P109+Q109)-(MIN(N109,N($E$9))+MIN(O109,N($E$10))))) -> 0 | S109: =MAX(0,MIN(N109,$C$14-(P109+Q109+R109)-(MIN(O109,N($E$10))))) -> 0 | T109: =MAX(0,MIN(O109,$C$14-(P109+Q109+R109+S109)-(0))) -> 0 | U109: =ROUND(K109-P109,2) -> 0 | V109: =ROUND(L109-Q109,2) -> 0 | W109: =ROUND(M109-R109,2) -> 0 | X109: =ROUND(N109-S109,2) -> 0 | Y109: =ROUND(O109-T109,2) -> 0 | Z109: =SUM(U109:Y109) -> 0
J110: =EDATE($C$13,69) -> 48488 | K110: =U109*(1+N($D$6)/12) -> 0 | L110: =V109*(1+N($D$7)/12) -> 0 | M110: =W109*(1+N($D$8)/12) -> 0 | N110: =X109*(1+N($D$9)/12) -> 0 | O110: =Y109*(1+N($D$10)/12) -> 0 | P110: =MAX(0,MIN(K110,$C$14-(0)-(MIN(L110,N($E$7))+MIN(M110,N($E$8))+MIN(N110,N($E$9))+MIN(O110,N($E$10))))) -> 0 | Q110: =MAX(0,MIN(L110,$C$14-(P110)-(MIN(M110,N($E$8))+MIN(N110,N($E$9))+MIN(O110,N($E$10))))) -> 0 | R110: =MAX(0,MIN(M110,$C$14-(P110+Q110)-(MIN(N110,N($E$9))+MIN(O110,N($E$10))))) -> 0 | S110: =MAX(0,MIN(N110,$C$14-(P110+Q110+R110)-(MIN(O110,N($E$10))))) -> 0 | T110: =MAX(0,MIN(O110,$C$14-(P110+Q110+R110+S110)-(0))) -> 0 | U110: =ROUND(K110-P110,2) -> 0 | V110: =ROUND(L110-Q110,2) -> 0 | W110: =ROUND(M110-R110,2) -> 0 | X110: =ROUND(N110-S110,2) -> 0 | Y110: =ROUND(O110-T110,2) -> 0 | Z110: =SUM(U110:Y110) -> 0
J111: =EDATE($C$13,70) -> 48519 | K111: =U110*(1+N($D$6)/12) -> 0 | L111: =V110*(1+N($D$7)/12) -> 0 | M111: =W110*(1+N($D$8)/12) -> 0 | N111: =X110*(1+N($D$9)/12) -> 0 | O111: =Y110*(1+N($D$10)/12) -> 0 | P111: =MAX(0,MIN(K111,$C$14-(0)-(MIN(L111,N($E$7))+MIN(M111,N($E$8))+MIN(N111,N($E$9))+MIN(O111,N($E$10))))) -> 0 | Q111: =MAX(0,MIN(L111,$C$14-(P111)-(MIN(M111,N($E$8))+MIN(N111,N($E$9))+MIN(O111,N($E$10))))) -> 0 | R111: =MAX(0,MIN(M111,$C$14-(P111+Q111)-(MIN(N111,N($E$9))+MIN(O111,N($E$10))))) -> 0 | S111: =MAX(0,MIN(N111,$C$14-(P111+Q111+R111)-(MIN(O111,N($E$10))))) -> 0 | T111: =MAX(0,MIN(O111,$C$14-(P111+Q111+R111+S111)-(0))) -> 0 | U111: =ROUND(K111-P111,2) -> 0 | V111: =ROUND(L111-Q111,2) -> 0 | W111: =ROUND(M111-R111,2) -> 0 | X111: =ROUND(N111-S111,2) -> 0 | Y111: =ROUND(O111-T111,2) -> 0 | Z111: =SUM(U111:Y111) -> 0
J112: =EDATE($C$13,71) -> 48549 | K112: =U111*(1+N($D$6)/12) -> 0 | L112: =V111*(1+N($D$7)/12) -> 0 | M112: =W111*(1+N($D$8)/12) -> 0 | N112: =X111*(1+N($D$9)/12) -> 0 | O112: =Y111*(1+N($D$10)/12) -> 0 | P112: =MAX(0,MIN(K112,$C$14-(0)-(MIN(L112,N($E$7))+MIN(M112,N($E$8))+MIN(N112,N($E$9))+MIN(O112,N($E$10))))) -> 0 | Q112: =MAX(0,MIN(L112,$C$14-(P112)-(MIN(M112,N($E$8))+MIN(N112,N($E$9))+MIN(O112,N($E$10))))) -> 0 | R112: =MAX(0,MIN(M112,$C$14-(P112+Q112)-(MIN(N112,N($E$9))+MIN(O112,N($E$10))))) -> 0 | S112: =MAX(0,MIN(N112,$C$14-(P112+Q112+R112)-(MIN(O112,N($E$10))))) -> 0 | T112: =MAX(0,MIN(O112,$C$14-(P112+Q112+R112+S112)-(0))) -> 0 | U112: =ROUND(K112-P112,2) -> 0 | V112: =ROUND(L112-Q112,2) -> 0 | W112: =ROUND(M112-R112,2) -> 0 | X112: =ROUND(N112-S112,2) -> 0 | Y112: =ROUND(O112-T112,2) -> 0 | Z112: =SUM(U112:Y112) -> 0
J113: =EDATE($C$13,72) -> 48580 | K113: =U112*(1+N($D$6)/12) -> 0 | L113: =V112*(1+N($D$7)/12) -> 0 | M113: =W112*(1+N($D$8)/12) -> 0 | N113: =X112*(1+N($D$9)/12) -> 0 | O113: =Y112*(1+N($D$10)/12) -> 0 | P113: =MAX(0,MIN(K113,$C$14-(0)-(MIN(L113,N($E$7))+MIN(M113,N($E$8))+MIN(N113,N($E$9))+MIN(O113,N($E$10))))) -> 0 | Q113: =MAX(0,MIN(L113,$C$14-(P113)-(MIN(M113,N($E$8))+MIN(N113,N($E$9))+MIN(O113,N($E$10))))) -> 0 | R113: =MAX(0,MIN(M113,$C$14-(P113+Q113)-(MIN(N113,N($E$9))+MIN(O113,N($E$10))))) -> 0 | S113: =MAX(0,MIN(N113,$C$14-(P113+Q113+R113)-(MIN(O113,N($E$10))))) -> 0 | T113: =MAX(0,MIN(O113,$C$14-(P113+Q113+R113+S113)-(0))) -> 0 | U113: =ROUND(K113-P113,2) -> 0 | V113: =ROUND(L113-Q113,2) -> 0 | W113: =ROUND(M113-R113,2) -> 0 | X113: =ROUND(N113-S113,2) -> 0 | Y113: =ROUND(O113-T113,2) -> 0 | Z113: =SUM(U113:Y113) -> 0
J114: =EDATE($C$13,73) -> 48611 | K114: =U113*(1+N($D$6)/12) -> 0 | L114: =V113*(1+N($D$7)/12) -> 0 | M114: =W113*(1+N($D$8)/12) -> 0 | N114: =X113*(1+N($D$9)/12) -> 0 | O114: =Y113*(1+N($D$10)/12) -> 0 | P114: =MAX(0,MIN(K114,$C$14-(0)-(MIN(L114,N($E$7))+MIN(M114,N($E$8))+MIN(N114,N($E$9))+MIN(O114,N($E$10))))) -> 0 | Q114: =MAX(0,MIN(L114,$C$14-(P114)-(MIN(M114,N($E$8))+MIN(N114,N($E$9))+MIN(O114,N($E$10))))) -> 0 | R114: =MAX(0,MIN(M114,$C$14-(P114+Q114)-(MIN(N114,N($E$9))+MIN(O114,N($E$10))))) -> 0 | S114: =MAX(0,MIN(N114,$C$14-(P114+Q114+R114)-(MIN(O114,N($E$10))))) -> 0 | T114: =MAX(0,MIN(O114,$C$14-(P114+Q114+R114+S114)-(0))) -> 0 | U114: =ROUND(K114-P114,2) -> 0 | V114: =ROUND(L114-Q114,2) -> 0 | W114: =ROUND(M114-R114,2) -> 0 | X114: =ROUND(N114-S114,2) -> 0 | Y114: =ROUND(O114-T114,2) -> 0 | Z114: =SUM(U114:Y114) -> 0
J115: =EDATE($C$13,74) -> 48639 | K115: =U114*(1+N($D$6)/12) -> 0 | L115: =V114*(1+N($D$7)/12) -> 0 | M115: =W114*(1+N($D$8)/12) -> 0 | N115: =X114*(1+N($D$9)/12) -> 0 | O115: =Y114*(1+N($D$10)/12) -> 0 | P115: =MAX(0,MIN(K115,$C$14-(0)-(MIN(L115,N($E$7))+MIN(M115,N($E$8))+MIN(N115,N($E$9))+MIN(O115,N($E$10))))) -> 0 | Q115: =MAX(0,MIN(L115,$C$14-(P115)-(MIN(M115,N($E$8))+MIN(N115,N($E$9))+MIN(O115,N($E$10))))) -> 0 | R115: =MAX(0,MIN(M115,$C$14-(P115+Q115)-(MIN(N115,N($E$9))+MIN(O115,N($E$10))))) -> 0 | S115: =MAX(0,MIN(N115,$C$14-(P115+Q115+R115)-(MIN(O115,N($E$10))))) -> 0 | T115: =MAX(0,MIN(O115,$C$14-(P115+Q115+R115+S115)-(0))) -> 0 | U115: =ROUND(K115-P115,2) -> 0 | V115: =ROUND(L115-Q115,2) -> 0 | W115: =ROUND(M115-R115,2) -> 0 | X115: =ROUND(N115-S115,2) -> 0 | Y115: =ROUND(O115-T115,2) -> 0 | Z115: =SUM(U115:Y115) -> 0
J116: =EDATE($C$13,75) -> 48670 | K116: =U115*(1+N($D$6)/12) -> 0 | L116: =V115*(1+N($D$7)/12) -> 0 | M116: =W115*(1+N($D$8)/12) -> 0 | N116: =X115*(1+N($D$9)/12) -> 0 | O116: =Y115*(1+N($D$10)/12) -> 0 | P116: =MAX(0,MIN(K116,$C$14-(0)-(MIN(L116,N($E$7))+MIN(M116,N($E$8))+MIN(N116,N($E$9))+MIN(O116,N($E$10))))) -> 0 | Q116: =MAX(0,MIN(L116,$C$14-(P116)-(MIN(M116,N($E$8))+MIN(N116,N($E$9))+MIN(O116,N($E$10))))) -> 0 | R116: =MAX(0,MIN(M116,$C$14-(P116+Q116)-(MIN(N116,N($E$9))+MIN(O116,N($E$10))))) -> 0 | S116: =MAX(0,MIN(N116,$C$14-(P116+Q116+R116)-(MIN(O116,N($E$10))))) -> 0 | T116: =MAX(0,MIN(O116,$C$14-(P116+Q116+R116+S116)-(0))) -> 0 | U116: =ROUND(K116-P116,2) -> 0 | V116: =ROUND(L116-Q116,2) -> 0 | W116: =ROUND(M116-R116,2) -> 0 | X116: =ROUND(N116-S116,2) -> 0 | Y116: =ROUND(O116-T116,2) -> 0 | Z116: =SUM(U116:Y116) -> 0
J117: =EDATE($C$13,76) -> 48700 | K117: =U116*(1+N($D$6)/12) -> 0 | L117: =V116*(1+N($D$7)/12) -> 0 | M117: =W116*(1+N($D$8)/12) -> 0 | N117: =X116*(1+N($D$9)/12) -> 0 | O117: =Y116*(1+N($D$10)/12) -> 0 | P117: =MAX(0,MIN(K117,$C$14-(0)-(MIN(L117,N($E$7))+MIN(M117,N($E$8))+MIN(N117,N($E$9))+MIN(O117,N($E$10))))) -> 0 | Q117: =MAX(0,MIN(L117,$C$14-(P117)-(MIN(M117,N($E$8))+MIN(N117,N($E$9))+MIN(O117,N($E$10))))) -> 0 | R117: =MAX(0,MIN(M117,$C$14-(P117+Q117)-(MIN(N117,N($E$9))+MIN(O117,N($E$10))))) -> 0 | S117: =MAX(0,MIN(N117,$C$14-(P117+Q117+R117)-(MIN(O117,N($E$10))))) -> 0 | T117: =MAX(0,MIN(O117,$C$14-(P117+Q117+R117+S117)-(0))) -> 0 | U117: =ROUND(K117-P117,2) -> 0 | V117: =ROUND(L117-Q117,2) -> 0 | W117: =ROUND(M117-R117,2) -> 0 | X117: =ROUND(N117-S117,2) -> 0 | Y117: =ROUND(O117-T117,2) -> 0 | Z117: =SUM(U117:Y117) -> 0
J118: =EDATE($C$13,77) -> 48731 | K118: =U117*(1+N($D$6)/12) -> 0 | L118: =V117*(1+N($D$7)/12) -> 0 | M118: =W117*(1+N($D$8)/12) -> 0 | N118: =X117*(1+N($D$9)/12) -> 0 | O118: =Y117*(1+N($D$10)/12) -> 0 | P118: =MAX(0,MIN(K118,$C$14-(0)-(MIN(L118,N($E$7))+MIN(M118,N($E$8))+MIN(N118,N($E$9))+MIN(O118,N($E$10))))) -> 0 | Q118: =MAX(0,MIN(L118,$C$14-(P118)-(MIN(M118,N($E$8))+MIN(N118,N($E$9))+MIN(O118,N($E$10))))) -> 0 | R118: =MAX(0,MIN(M118,$C$14-(P118+Q118)-(MIN(N118,N($E$9))+MIN(O118,N($E$10))))) -> 0 | S118: =MAX(0,MIN(N118,$C$14-(P118+Q118+R118)-(MIN(O118,N($E$10))))) -> 0 | T118: =MAX(0,MIN(O118,$C$14-(P118+Q118+R118+S118)-(0))) -> 0 | U118: =ROUND(K118-P118,2) -> 0 | V118: =ROUND(L118-Q118,2) -> 0 | W118: =ROUND(M118-R118,2) -> 0 | X118: =ROUND(N118-S118,2) -> 0 | Y118: =ROUND(O118-T118,2) -> 0 | Z118: =SUM(U118:Y118) -> 0
J119: =EDATE($C$13,78) -> 48761 | K119: =U118*(1+N($D$6)/12) -> 0 | L119: =V118*(1+N($D$7)/12) -> 0 | M119: =W118*(1+N($D$8)/12) -> 0 | N119: =X118*(1+N($D$9)/12) -> 0 | O119: =Y118*(1+N($D$10)/12) -> 0 | P119: =MAX(0,MIN(K119,$C$14-(0)-(MIN(L119,N($E$7))+MIN(M119,N($E$8))+MIN(N119,N($E$9))+MIN(O119,N($E$10))))) -> 0 | Q119: =MAX(0,MIN(L119,$C$14-(P119)-(MIN(M119,N($E$8))+MIN(N119,N($E$9))+MIN(O119,N($E$10))))) -> 0 | R119: =MAX(0,MIN(M119,$C$14-(P119+Q119)-(MIN(N119,N($E$9))+MIN(O119,N($E$10))))) -> 0 | S119: =MAX(0,MIN(N119,$C$14-(P119+Q119+R119)-(MIN(O119,N($E$10))))) -> 0 | T119: =MAX(0,MIN(O119,$C$14-(P119+Q119+R119+S119)-(0))) -> 0 | U119: =ROUND(K119-P119,2) -> 0 | V119: =ROUND(L119-Q119,2) -> 0 | W119: =ROUND(M119-R119,2) -> 0 | X119: =ROUND(N119-S119,2) -> 0 | Y119: =ROUND(O119-T119,2) -> 0 | Z119: =SUM(U119:Y119) -> 0
J120: =EDATE($C$13,79) -> 48792 | K120: =U119*(1+N($D$6)/12) -> 0 | L120: =V119*(1+N($D$7)/12) -> 0 | M120: =W119*(1+N($D$8)/12) -> 0 | N120: =X119*(1+N($D$9)/12) -> 0 | O120: =Y119*(1+N($D$10)/12) -> 0 | P120: =MAX(0,MIN(K120,$C$14-(0)-(MIN(L120,N($E$7))+MIN(M120,N($E$8))+MIN(N120,N($E$9))+MIN(O120,N($E$10))))) -> 0 | Q120: =MAX(0,MIN(L120,$C$14-(P120)-(MIN(M120,N($E$8))+MIN(N120,N($E$9))+MIN(O120,N($E$10))))) -> 0 | R120: =MAX(0,MIN(M120,$C$14-(P120+Q120)-(MIN(N120,N($E$9))+MIN(O120,N($E$10))))) -> 0 | S120: =MAX(0,MIN(N120,$C$14-(P120+Q120+R120)-(MIN(O120,N($E$10))))) -> 0 | T120: =MAX(0,MIN(O120,$C$14-(P120+Q120+R120+S120)-(0))) -> 0 | U120: =ROUND(K120-P120,2) -> 0 | V120: =ROUND(L120-Q120,2) -> 0 | W120: =ROUND(M120-R120,2) -> 0 | X120: =ROUND(N120-S120,2) -> 0 | Y120: =ROUND(O120-T120,2) -> 0 | Z120: =SUM(U120:Y120) -> 0
J121: =EDATE($C$13,80) -> 48823 | K121: =U120*(1+N($D$6)/12) -> 0 | L121: =V120*(1+N($D$7)/12) -> 0 | M121: =W120*(1+N($D$8)/12) -> 0 | N121: =X120*(1+N($D$9)/12) -> 0 | O121: =Y120*(1+N($D$10)/12) -> 0 | P121: =MAX(0,MIN(K121,$C$14-(0)-(MIN(L121,N($E$7))+MIN(M121,N($E$8))+MIN(N121,N($E$9))+MIN(O121,N($E$10))))) -> 0 | Q121: =MAX(0,MIN(L121,$C$14-(P121)-(MIN(M121,N($E$8))+MIN(N121,N($E$9))+MIN(O121,N($E$10))))) -> 0 | R121: =MAX(0,MIN(M121,$C$14-(P121+Q121)-(MIN(N121,N($E$9))+MIN(O121,N($E$10))))) -> 0 | S121: =MAX(0,MIN(N121,$C$14-(P121+Q121+R121)-(MIN(O121,N($E$10))))) -> 0 | T121: =MAX(0,MIN(O121,$C$14-(P121+Q121+R121+S121)-(0))) -> 0 | U121: =ROUND(K121-P121,2) -> 0 | V121: =ROUND(L121-Q121,2) -> 0 | W121: =ROUND(M121-R121,2) -> 0 | X121: =ROUND(N121-S121,2) -> 0 | Y121: =ROUND(O121-T121,2) -> 0 | Z121: =SUM(U121:Y121) -> 0
J122: =EDATE($C$13,81) -> 48853 | K122: =U121*(1+N($D$6)/12) -> 0 | L122: =V121*(1+N($D$7)/12) -> 0 | M122: =W121*(1+N($D$8)/12) -> 0 | N122: =X121*(1+N($D$9)/12) -> 0 | O122: =Y121*(1+N($D$10)/12) -> 0 | P122: =MAX(0,MIN(K122,$C$14-(0)-(MIN(L122,N($E$7))+MIN(M122,N($E$8))+MIN(N122,N($E$9))+MIN(O122,N($E$10))))) -> 0 | Q122: =MAX(0,MIN(L122,$C$14-(P122)-(MIN(M122,N($E$8))+MIN(N122,N($E$9))+MIN(O122,N($E$10))))) -> 0 | R122: =MAX(0,MIN(M122,$C$14-(P122+Q122)-(MIN(N122,N($E$9))+MIN(O122,N($E$10))))) -> 0 | S122: =MAX(0,MIN(N122,$C$14-(P122+Q122+R122)-(MIN(O122,N($E$10))))) -> 0 | T122: =MAX(0,MIN(O122,$C$14-(P122+Q122+R122+S122)-(0))) -> 0 | U122: =ROUND(K122-P122,2) -> 0 | V122: =ROUND(L122-Q122,2) -> 0 | W122: =ROUND(M122-R122,2) -> 0 | X122: =ROUND(N122-S122,2) -> 0 | Y122: =ROUND(O122-T122,2) -> 0 | Z122: =SUM(U122:Y122) -> 0
J123: =EDATE($C$13,82) -> 48884 | K123: =U122*(1+N($D$6)/12) -> 0 | L123: =V122*(1+N($D$7)/12) -> 0 | M123: =W122*(1+N($D$8)/12) -> 0 | N123: =X122*(1+N($D$9)/12) -> 0 | O123: =Y122*(1+N($D$10)/12) -> 0 | P123: =MAX(0,MIN(K123,$C$14-(0)-(MIN(L123,N($E$7))+MIN(M123,N($E$8))+MIN(N123,N($E$9))+MIN(O123,N($E$10))))) -> 0 | Q123: =MAX(0,MIN(L123,$C$14-(P123)-(MIN(M123,N($E$8))+MIN(N123,N($E$9))+MIN(O123,N($E$10))))) -> 0 | R123: =MAX(0,MIN(M123,$C$14-(P123+Q123)-(MIN(N123,N($E$9))+MIN(O123,N($E$10))))) -> 0 | S123: =MAX(0,MIN(N123,$C$14-(P123+Q123+R123)-(MIN(O123,N($E$10))))) -> 0 | T123: =MAX(0,MIN(O123,$C$14-(P123+Q123+R123+S123)-(0))) -> 0 | U123: =ROUND(K123-P123,2) -> 0 | V123: =ROUND(L123-Q123,2) -> 0 | W123: =ROUND(M123-R123,2) -> 0 | X123: =ROUND(N123-S123,2) -> 0 | Y123: =ROUND(O123-T123,2) -> 0 | Z123: =SUM(U123:Y123) -> 0
J124: =EDATE($C$13,83) -> 48914 | K124: =U123*(1+N($D$6)/12) -> 0 | L124: =V123*(1+N($D$7)/12) -> 0 | M124: =W123*(1+N($D$8)/12) -> 0 | N124: =X123*(1+N($D$9)/12) -> 0 | O124: =Y123*(1+N($D$10)/12) -> 0 | P124: =MAX(0,MIN(K124,$C$14-(0)-(MIN(L124,N($E$7))+MIN(M124,N($E$8))+MIN(N124,N($E$9))+MIN(O124,N($E$10))))) -> 0 | Q124: =MAX(0,MIN(L124,$C$14-(P124)-(MIN(M124,N($E$8))+MIN(N124,N($E$9))+MIN(O124,N($E$10))))) -> 0 | R124: =MAX(0,MIN(M124,$C$14-(P124+Q124)-(MIN(N124,N($E$9))+MIN(O124,N($E$10))))) -> 0 | S124: =MAX(0,MIN(N124,$C$14-(P124+Q124+R124)-(MIN(O124,N($E$10))))) -> 0 | T124: =MAX(0,MIN(O124,$C$14-(P124+Q124+R124+S124)-(0))) -> 0 | U124: =ROUND(K124-P124,2) -> 0 | V124: =ROUND(L124-Q124,2) -> 0 | W124: =ROUND(M124-R124,2) -> 0 | X124: =ROUND(N124-S124,2) -> 0 | Y124: =ROUND(O124-T124,2) -> 0 | Z124: =SUM(U124:Y124) -> 0
J125: =EDATE($C$13,84) -> 48945 | K125: =U124*(1+N($D$6)/12) -> 0 | L125: =V124*(1+N($D$7)/12) -> 0 | M125: =W124*(1+N($D$8)/12) -> 0 | N125: =X124*(1+N($D$9)/12) -> 0 | O125: =Y124*(1+N($D$10)/12) -> 0 | P125: =MAX(0,MIN(K125,$C$14-(0)-(MIN(L125,N($E$7))+MIN(M125,N($E$8))+MIN(N125,N($E$9))+MIN(O125,N($E$10))))) -> 0 | Q125: =MAX(0,MIN(L125,$C$14-(P125)-(MIN(M125,N($E$8))+MIN(N125,N($E$9))+MIN(O125,N($E$10))))) -> 0 | R125: =MAX(0,MIN(M125,$C$14-(P125+Q125)-(MIN(N125,N($E$9))+MIN(O125,N($E$10))))) -> 0 | S125: =MAX(0,MIN(N125,$C$14-(P125+Q125+R125)-(MIN(O125,N($E$10))))) -> 0 | T125: =MAX(0,MIN(O125,$C$14-(P125+Q125+R125+S125)-(0))) -> 0 | U125: =ROUND(K125-P125,2) -> 0 | V125: =ROUND(L125-Q125,2) -> 0 | W125: =ROUND(M125-R125,2) -> 0 | X125: =ROUND(N125-S125,2) -> 0 | Y125: =ROUND(O125-T125,2) -> 0 | Z125: =SUM(U125:Y125) -> 0
J126: =EDATE($C$13,85) -> 48976 | K126: =U125*(1+N($D$6)/12) -> 0 | L126: =V125*(1+N($D$7)/12) -> 0 | M126: =W125*(1+N($D$8)/12) -> 0 | N126: =X125*(1+N($D$9)/12) -> 0 | O126: =Y125*(1+N($D$10)/12) -> 0 | P126: =MAX(0,MIN(K126,$C$14-(0)-(MIN(L126,N($E$7))+MIN(M126,N($E$8))+MIN(N126,N($E$9))+MIN(O126,N($E$10))))) -> 0 | Q126: =MAX(0,MIN(L126,$C$14-(P126)-(MIN(M126,N($E$8))+MIN(N126,N($E$9))+MIN(O126,N($E$10))))) -> 0 | R126: =MAX(0,MIN(M126,$C$14-(P126+Q126)-(MIN(N126,N($E$9))+MIN(O126,N($E$10))))) -> 0 | S126: =MAX(0,MIN(N126,$C$14-(P126+Q126+R126)-(MIN(O126,N($E$10))))) -> 0 | T126: =MAX(0,MIN(O126,$C$14-(P126+Q126+R126+S126)-(0))) -> 0 | U126: =ROUND(K126-P126,2) -> 0 | V126: =ROUND(L126-Q126,2) -> 0 | W126: =ROUND(M126-R126,2) -> 0 | X126: =ROUND(N126-S126,2) -> 0 | Y126: =ROUND(O126-T126,2) -> 0 | Z126: =SUM(U126:Y126) -> 0
...

Sheet Savings Goals
B2: Savings Goals
B3: Give every goal a date. Sorted works out the monthly amount.
B5: Goal | C5: Target | D5: Saved so far | E5: Target date | F5: Months left | G5: Save per month | H5: Progress
B6: Emergency fund (3 months) | C6: 9000 | D6: 2400 | E6: =EDATE(TODAY(),12) -> 46661 | F6: =IF(OR(B6="",E6=""),"",MAX(1,(YEAR(E6)-YEAR(TODAY()))*12+MONTH(E6)-MONTH(TODAY()))) -> 12 | G6: =IF(F6="","",MAX(0,(C6-D6)/F6)) -> 550 | H6: =IF(N(C6)=0,"",MIN(1,D6/C6)) -> 0.26666667
B7: Summer holiday | C7: 2500 | D7: 600 | E7: =EDATE(TODAY(),7) -> 46508 | F7: =IF(OR(B7="",E7=""),"",MAX(1,(YEAR(E7)-YEAR(TODAY()))*12+MONTH(E7)-MONTH(TODAY()))) -> 7 | G7: =IF(F7="","",MAX(0,(C7-D7)/F7)) -> 271.42857 | H7: =IF(N(C7)=0,"",MIN(1,D7/C7)) -> 0.24
B8: New laptop | C8: 1400 | D8: 350 | E8: =EDATE(TODAY(),5) -> 46447 | F8: =IF(OR(B8="",E8=""),"",MAX(1,(YEAR(E8)-YEAR(TODAY()))*12+MONTH(E8)-MONTH(TODAY()))) -> 5 | G8: =IF(F8="","",MAX(0,(C8-D8)/F8)) -> 210 | H8: =IF(N(C8)=0,"",MIN(1,D8/C8)) -> 0.25
B9: House deposit | C9: 30000 | D9: 4200 | E9: =EDATE(TODAY(),36) -> 47392 | F9: =IF(OR(B9="",E9=""),"",MAX(1,(YEAR(E9)-YEAR(TODAY()))*12+MONTH(E9)-MONTH(TODAY()))) -> 36 | G9: =IF(F9="","",MAX(0,(C9-D9)/F9)) -> 716.66667 | H9: =IF(N(C9)=0,"",MIN(1,D9/C9)) -> 0.14
F10: =IF(OR(B10="",E10=""),"",MAX(1,(YEAR(E10)-YEAR(TODAY()))*12+MONTH(E10)-MONTH(TODAY()))) | G10: =IF(F10="","",MAX(0,(C10-D10)/F10)) | H10: =IF(N(C10)=0,"",MIN(1,D10/C10))
F11: =IF(OR(B11="",E11=""),"",MAX(1,(YEAR(E11)-YEAR(TODAY()))*12+MONTH(E11)-MONTH(TODAY()))) | G11: =IF(F11="","",MAX(0,(C11-D11)/F11)) | H11: =IF(N(C11)=0,"",MIN(1,D11/C11))
F12: =IF(OR(B12="",E12=""),"",MAX(1,(YEAR(E12)-YEAR(TODAY()))*12+MONTH(E12)-MONTH(TODAY()))) | G12: =IF(F12="","",MAX(0,(C12-D12)/F12)) | H12: =IF(N(C12)=0,"",MIN(1,D12/C12))
F13: =IF(OR(B13="",E13=""),"",MAX(1,(YEAR(E13)-YEAR(TODAY()))*12+MONTH(E13)-MONTH(TODAY()))) | G13: =IF(F13="","",MAX(0,(C13-D13)/F13)) | H13: =IF(N(C13)=0,"",MIN(1,D13/C13))
F14: =IF(OR(B14="",E14=""),"",MAX(1,(YEAR(E14)-YEAR(TODAY()))*12+MONTH(E14)-MONTH(TODAY()))) | G14: =IF(F14="","",MAX(0,(C14-D14)/F14)) | H14: =IF(N(C14)=0,"",MIN(1,D14/C14))
F15: =IF(OR(B15="",E15=""),"",MAX(1,(YEAR(E15)-YEAR(TODAY()))*12+MONTH(E15)-MONTH(TODAY()))) | G15: =IF(F15="","",MAX(0,(C15-D15)/F15)) | H15: =IF(N(C15)=0,"",MIN(1,D15/C15))
F16: =IF(OR(B16="",E16=""),"",MAX(1,(YEAR(E16)-YEAR(TODAY()))*12+MONTH(E16)-MONTH(TODAY()))) | G16: =IF(F16="","",MAX(0,(C16-D16)/F16)) | H16: =IF(N(C16)=0,"",MIN(1,D16/C16))
F17: =IF(OR(B17="",E17=""),"",MAX(1,(YEAR(E17)-YEAR(TODAY()))*12+MONTH(E17)-MONTH(TODAY()))) | G17: =IF(F17="","",MAX(0,(C17-D17)/F17)) | H17: =IF(N(C17)=0,"",MIN(1,D17/C17))
B19: Total to set aside each month | G19: =SUM(G6:G17) -> 1748.0952
B20: Compare this with your Savings budget on the Setup tab.
